<?xml version="1.0" encoding="UTF-8"?>
<export version="D">
  <design>
    <source>/home/robert/ownCloud/Electronics/Projects/NixieClock_2017/PCB/esp_nixie_clock.sch</source>
    <date>otrdiena, 2017. gada 21. novembris, plkst. 15 un 48</date>
    <tool>Eeschema 4.0.7-e2-6376~58~ubuntu16.04.1</tool>
    <sheet number="1" name="/" tstamps="/">
      <title_block>
        <title>Nixie Clock with IN-14 tubes and ESP8266 MCU</title>
        <company>Roberts Gotlaufs</company>
        <rev>1.0</rev>
        <date>2017-11-02</date>
        <source>esp_nixie_clock.sch</source>
        <comment number="1" value=""/>
        <comment number="2" value=""/>
        <comment number="3" value=""/>
        <comment number="4" value=""/>
      </title_block>
    </sheet>
    <sheet number="2" name="/3V3 power/" tstamps="/59EB6C5A/">
      <title_block>
        <title>Nixie Clock with IN-14 tubes and ESP8266 MCU</title>
        <company>Roberts Gotlaufs</company>
        <rev>1.0</rev>
        <date>2017-11-02</date>
        <source>power_3V3.sch</source>
        <comment number="1" value=""/>
        <comment number="2" value=""/>
        <comment number="3" value=""/>
        <comment number="4" value=""/>
      </title_block>
    </sheet>
    <sheet number="3" name="/HV power/" tstamps="/59EB6C7E/">
      <title_block>
        <title>Nixie Clock with IN-14 tubes and ESP8266 MCU</title>
        <company>Roberts Gotlaufs</company>
        <rev>1.0</rev>
        <date>2017-11-02</date>
        <source>power_HV.sch</source>
        <comment number="1" value=""/>
        <comment number="2" value=""/>
        <comment number="3" value=""/>
        <comment number="4" value=""/>
      </title_block>
    </sheet>
    <sheet number="4" name="/Real Time Clock/" tstamps="/59EB6D1A/">
      <title_block>
        <title>Nixie Clock with IN-14 tubes and ESP8266 MCU</title>
        <company>Roberts Gotlaufs</company>
        <rev>1.0</rev>
        <date>2017-11-02</date>
        <source>rtc.sch</source>
        <comment number="1" value=""/>
        <comment number="2" value=""/>
        <comment number="3" value=""/>
        <comment number="4" value=""/>
      </title_block>
    </sheet>
    <sheet number="5" name="/User I/O/" tstamps="/59EB6D2B/">
      <title_block>
        <title>Nixie Clock with IN-14 tubes and ESP8266 MCU</title>
        <company>Roberts Gotlaufs</company>
        <rev>1.0</rev>
        <date>2017-11-02</date>
        <source>gpio.sch</source>
        <comment number="1" value=""/>
        <comment number="2" value=""/>
        <comment number="3" value=""/>
        <comment number="4" value=""/>
      </title_block>
    </sheet>
    <sheet number="6" name="/Input power/" tstamps="/59EB6DF5/">
      <title_block>
        <title>Nixie Clock with IN-14 tubes and ESP8266 MCU</title>
        <company>Roberts Gotlaufs</company>
        <rev>1.0</rev>
        <date>2017-11-02</date>
        <source>power_in.sch</source>
        <comment number="1" value=""/>
        <comment number="2" value=""/>
        <comment number="3" value=""/>
        <comment number="4" value=""/>
      </title_block>
    </sheet>
    <sheet number="7" name="/MCU ESP-12/" tstamps="/59EB6C93/">
      <title_block>
        <title>Nixie Clock with IN-14 tubes and ESP8266 MCU</title>
        <company>Roberts Gotlaufs</company>
        <rev>1.0</rev>
        <date>2017-11-02</date>
        <source>esp12.sch</source>
        <comment number="1" value=""/>
        <comment number="2" value=""/>
        <comment number="3" value=""/>
        <comment number="4" value=""/>
      </title_block>
    </sheet>
    <sheet number="8" name="/Nixie Tube drivers/" tstamps="/59EB6CE0/">
      <title_block>
        <title>Nixie Clock with IN-14 tubes and ESP8266 MCU</title>
        <company>Roberts Gotlaufs</company>
        <rev>1.0</rev>
        <date>2017-11-02</date>
        <source>nixie_drivers.sch</source>
        <comment number="1" value=""/>
        <comment number="2" value=""/>
        <comment number="3" value=""/>
        <comment number="4" value=""/>
      </title_block>
    </sheet>
    <sheet number="9" name="/Nixie Tubes/" tstamps="/59EB6D02/">
      <title_block>
        <title>Nixie Clock with IN-14 tubes and ESP8266 MCU</title>
        <company>Roberts Gotlaufs</company>
        <rev>1.0</rev>
        <date>2017-11-02</date>
        <source>nixie_tubes.sch</source>
        <comment number="1" value=""/>
        <comment number="2" value=""/>
        <comment number="3" value=""/>
        <comment number="4" value=""/>
      </title_block>
    </sheet>
    <sheet number="10" name="/Programmable LEDs/" tstamps="/59FFB7E0/">
      <title_block>
        <title>Nixie Clock with IN-14 tubes and ESP8266 MCU</title>
        <company>Roberts Gotlaufs</company>
        <rev>1.0</rev>
        <date>2017-11-02</date>
        <source>ws2812.sch</source>
        <comment number="1" value=""/>
        <comment number="2" value=""/>
        <comment number="3" value=""/>
        <comment number="4" value=""/>
      </title_block>
    </sheet>
  </design>
  <components>
    <comp ref="MK1">
      <value>Mounting_Hole_PAD</value>
      <footprint>Mounting_Holes:MountingHole_3.2mm_M3_Pad_Via</footprint>
      <libsource lib="mechanical" part="Mounting_Hole_PAD"/>
      <sheetpath names="/" tstamps="/"/>
      <tstamp>59FB21A5</tstamp>
    </comp>
    <comp ref="MK3">
      <value>Mounting_Hole_PAD</value>
      <footprint>Mounting_Holes:MountingHole_3.2mm_M3_Pad_Via</footprint>
      <libsource lib="mechanical" part="Mounting_Hole_PAD"/>
      <sheetpath names="/" tstamps="/"/>
      <tstamp>59FB21AC</tstamp>
    </comp>
    <comp ref="MK2">
      <value>Mounting_Hole_PAD</value>
      <footprint>Mounting_Holes:MountingHole_3.2mm_M3_Pad_Via</footprint>
      <libsource lib="mechanical" part="Mounting_Hole_PAD"/>
      <sheetpath names="/" tstamps="/"/>
      <tstamp>59FB21B3</tstamp>
    </comp>
    <comp ref="MK4">
      <value>Mounting_Hole_PAD</value>
      <footprint>Mounting_Holes:MountingHole_3.2mm_M3_Pad_Via</footprint>
      <libsource lib="mechanical" part="Mounting_Hole_PAD"/>
      <sheetpath names="/" tstamps="/"/>
      <tstamp>59FB21BA</tstamp>
    </comp>
    <comp ref="F1">
      <value>Fiducial</value>
      <footprint>Fiducials:Fiducial_1mm_Dia_2.54mm_Outer_CopperTop</footprint>
      <libsource lib="components" part="Fiducial"/>
      <sheetpath names="/" tstamps="/"/>
      <tstamp>59FB21DD</tstamp>
    </comp>
    <comp ref="F2">
      <value>Fiducial</value>
      <footprint>Fiducials:Fiducial_1mm_Dia_2.54mm_Outer_CopperTop</footprint>
      <libsource lib="components" part="Fiducial"/>
      <sheetpath names="/" tstamps="/"/>
      <tstamp>59FB21E4</tstamp>
    </comp>
    <comp ref="F3">
      <value>Fiducial</value>
      <footprint>Fiducials:Fiducial_1mm_Dia_2.54mm_Outer_CopperTop</footprint>
      <libsource lib="components" part="Fiducial"/>
      <sheetpath names="/" tstamps="/"/>
      <tstamp>59FB21EB</tstamp>
    </comp>
    <comp ref="TP2">
      <value>TestPoint</value>
      <footprint>Measurement_Points:Measurement_Point_Round-SMD-Pad_Small</footprint>
      <libsource lib="components" part="TestPoint"/>
      <sheetpath names="/" tstamps="/"/>
      <tstamp>59FBD14F</tstamp>
    </comp>
    <comp ref="TP3">
      <value>TestPoint</value>
      <footprint>Measurement_Points:Measurement_Point_Round-SMD-Pad_Small</footprint>
      <libsource lib="components" part="TestPoint"/>
      <sheetpath names="/" tstamps="/"/>
      <tstamp>59FBD2B0</tstamp>
    </comp>
    <comp ref="TP5">
      <value>TestPoint</value>
      <footprint>Measurement_Points:Measurement_Point_Round-SMD-Pad_Small</footprint>
      <libsource lib="components" part="TestPoint"/>
      <sheetpath names="/" tstamps="/"/>
      <tstamp>59FBD3FD</tstamp>
    </comp>
    <comp ref="TP6">
      <value>TestPoint</value>
      <footprint>Measurement_Points:Measurement_Point_Round-SMD-Pad_Small</footprint>
      <libsource lib="components" part="TestPoint"/>
      <sheetpath names="/" tstamps="/"/>
      <tstamp>59FBD531</tstamp>
    </comp>
    <comp ref="TP1">
      <value>TestPoint</value>
      <footprint>Measurement_Points:Measurement_Point_Round-SMD-Pad_Small</footprint>
      <libsource lib="components" part="TestPoint"/>
      <sheetpath names="/" tstamps="/"/>
      <tstamp>59FC719E</tstamp>
    </comp>
    <comp ref="TP4">
      <value>TestPoint</value>
      <footprint>Measurement_Points:Measurement_Point_Round-SMD-Pad_Small</footprint>
      <libsource lib="components" part="TestPoint"/>
      <sheetpath names="/" tstamps="/"/>
      <tstamp>59FC72F6</tstamp>
    </comp>
    <comp ref="TP7">
      <value>TestPoint</value>
      <footprint>Measurement_Points:Measurement_Point_Round-SMD-Pad_Small</footprint>
      <libsource lib="components" part="TestPoint"/>
      <sheetpath names="/" tstamps="/"/>
      <tstamp>59FC743D</tstamp>
    </comp>
    <comp ref="U1">
      <value>MC34063</value>
      <footprint>Housings_SOIC:SOIC-8_3.9x4.9mm_Pitch1.27mm</footprint>
      <libsource lib="dc-dc" part="MC34063"/>
      <sheetpath names="/3V3 power/" tstamps="/59EB6C5A/"/>
      <tstamp>59F08954</tstamp>
    </comp>
    <comp ref="C2">
      <value>270p</value>
      <footprint>Capacitors_SMD:C_0805_HandSoldering</footprint>
      <libsource lib="device" part="C"/>
      <sheetpath names="/3V3 power/" tstamps="/59EB6C5A/"/>
      <tstamp>59F089D9</tstamp>
    </comp>
    <comp ref="C1">
      <value>100n</value>
      <footprint>Capacitors_SMD:C_0805_HandSoldering</footprint>
      <libsource lib="device" part="C"/>
      <sheetpath names="/3V3 power/" tstamps="/59EB6C5A/"/>
      <tstamp>59F0C0F9</tstamp>
    </comp>
    <comp ref="R1">
      <value>1k</value>
      <footprint>Resistors_SMD:R_0805_HandSoldering</footprint>
      <libsource lib="device" part="R"/>
      <sheetpath names="/3V3 power/" tstamps="/59EB6C5A/"/>
      <tstamp>59F0C6CD</tstamp>
    </comp>
    <comp ref="D1">
      <value>SS13 R3G</value>
      <footprint>Diodes_SMD:D_SMA</footprint>
      <libsource lib="device" part="D"/>
      <sheetpath names="/3V3 power/" tstamps="/59EB6C5A/"/>
      <tstamp>59F0D389</tstamp>
    </comp>
    <comp ref="L1">
      <value>100u</value>
      <footprint>footprints:L_100u</footprint>
      <libsource lib="device" part="L"/>
      <sheetpath names="/3V3 power/" tstamps="/59EB6C5A/"/>
      <tstamp>59F0D42D</tstamp>
    </comp>
    <comp ref="R2">
      <value>5.6k</value>
      <footprint>Resistors_SMD:R_0805_HandSoldering</footprint>
      <libsource lib="device" part="R"/>
      <sheetpath names="/3V3 power/" tstamps="/59EB6C5A/"/>
      <tstamp>59F0DE51</tstamp>
    </comp>
    <comp ref="R3">
      <value>3.3k</value>
      <footprint>Resistors_SMD:R_0805_HandSoldering</footprint>
      <libsource lib="device" part="R"/>
      <sheetpath names="/3V3 power/" tstamps="/59EB6C5A/"/>
      <tstamp>59F0DE8C</tstamp>
    </comp>
    <comp ref="RV1">
      <value>100k</value>
      <footprint>Potentiometers:Potentiometer_Trimmer_Bourns_3214G</footprint>
      <libsource lib="device" part="POT"/>
      <sheetpath names="/3V3 power/" tstamps="/59EB6C5A/"/>
      <tstamp>59F0DEC9</tstamp>
    </comp>
    <comp ref="C4">
      <value>10n</value>
      <footprint>Capacitors_SMD:C_0805_HandSoldering</footprint>
      <libsource lib="device" part="C"/>
      <sheetpath names="/3V3 power/" tstamps="/59EB6C5A/"/>
      <tstamp>59F11468</tstamp>
    </comp>
    <comp ref="C5">
      <value>220u</value>
      <footprint>Capacitors_SMD:CP_Elec_8x10</footprint>
      <fields>
        <field name="Manufacturer Part number">EMZR250ADA221MF80G</field>
      </fields>
      <libsource lib="device" part="CP"/>
      <sheetpath names="/3V3 power/" tstamps="/59EB6C5A/"/>
      <tstamp>59F0A8CC</tstamp>
    </comp>
    <comp ref="Q3">
      <value>NTF5P03T3G</value>
      <footprint>TO_SOT_Packages_SMD:SOT-223-3_TabPin2</footprint>
      <libsource lib="device" part="Q_PMOS_GDS"/>
      <sheetpath names="/3V3 power/" tstamps="/59EB6C5A/"/>
      <tstamp>59FB23A1</tstamp>
    </comp>
    <comp ref="Q1">
      <value>BC847BW</value>
      <footprint>TO_SOT_Packages_SMD:SOT-323_SC-70_Handsoldering</footprint>
      <libsource lib="device" part="Q_NPN_BEC"/>
      <sheetpath names="/3V3 power/" tstamps="/59EB6C5A/"/>
      <tstamp>59F9DC2F</tstamp>
    </comp>
    <comp ref="Q2">
      <value>BC857W</value>
      <footprint>TO_SOT_Packages_SMD:SOT-323_SC-70_Handsoldering</footprint>
      <libsource lib="transistors" part="BC857W"/>
      <sheetpath names="/3V3 power/" tstamps="/59EB6C5A/"/>
      <tstamp>59FA0E16</tstamp>
    </comp>
    <comp ref="TP8">
      <value>TestPoint</value>
      <footprint>Measurement_Points:Measurement_Point_Round-SMD-Pad_Small</footprint>
      <libsource lib="components" part="TestPoint"/>
      <sheetpath names="/3V3 power/" tstamps="/59EB6C5A/"/>
      <tstamp>59FD2069</tstamp>
    </comp>
    <comp ref="TP9">
      <value>TestPoint</value>
      <footprint>Measurement_Points:Measurement_Point_Round-SMD-Pad_Small</footprint>
      <libsource lib="components" part="TestPoint"/>
      <sheetpath names="/3V3 power/" tstamps="/59EB6C5A/"/>
      <tstamp>59FD274F</tstamp>
    </comp>
    <comp ref="C3">
      <value>220u</value>
      <footprint>Capacitors_SMD:CP_Elec_8x10</footprint>
      <fields>
        <field name="Manufacturer">Nichicon</field>
        <field name="Manufacturer Part Number">UWT1E221MNL1GS</field>
        <field name="Notes">25V</field>
      </fields>
      <libsource lib="device" part="CP"/>
      <sheetpath names="/3V3 power/" tstamps="/59EB6C5A/"/>
      <tstamp>5A03FE57</tstamp>
    </comp>
    <comp ref="U2">
      <value>MC34063</value>
      <footprint>Housings_SOIC:SOIC-8_3.9x4.9mm_Pitch1.27mm</footprint>
      <libsource lib="dc-dc" part="MC34063"/>
      <sheetpath names="/HV power/" tstamps="/59EB6C7E/"/>
      <tstamp>59F02785</tstamp>
    </comp>
    <comp ref="C8">
      <value>680p</value>
      <footprint>Capacitors_SMD:C_0805_HandSoldering</footprint>
      <libsource lib="device" part="C"/>
      <sheetpath names="/HV power/" tstamps="/59EB6C7E/"/>
      <tstamp>59F02993</tstamp>
    </comp>
    <comp ref="C7">
      <value>100n</value>
      <footprint>Capacitors_SMD:C_0805_HandSoldering</footprint>
      <libsource lib="device" part="C"/>
      <sheetpath names="/HV power/" tstamps="/59EB6C7E/"/>
      <tstamp>59F02A08</tstamp>
    </comp>
    <comp ref="D2">
      <value>1n4148</value>
      <footprint>Diodes_SMD:D_SOD-123</footprint>
      <libsource lib="device" part="D"/>
      <sheetpath names="/HV power/" tstamps="/59EB6C7E/"/>
      <tstamp>59F02BFF</tstamp>
    </comp>
    <comp ref="R6">
      <value>1k</value>
      <footprint>Resistors_SMD:R_0805_HandSoldering</footprint>
      <libsource lib="device" part="R"/>
      <sheetpath names="/HV power/" tstamps="/59EB6C7E/"/>
      <tstamp>59F02CD4</tstamp>
    </comp>
    <comp ref="L2">
      <value>150u</value>
      <footprint>Inductors_SMD:L_Wuerth_WE-PD-Typ-LS_Handsoldering</footprint>
      <libsource lib="device" part="L"/>
      <sheetpath names="/HV power/" tstamps="/59EB6C7E/"/>
      <tstamp>59F03948</tstamp>
    </comp>
    <comp ref="D3">
      <value>RS1GTR</value>
      <footprint>Diodes_SMD:D_SMA</footprint>
      <libsource lib="device" part="D"/>
      <sheetpath names="/HV power/" tstamps="/59EB6C7E/"/>
      <tstamp>59F04C53</tstamp>
    </comp>
    <comp ref="R7">
      <value>165k</value>
      <footprint>Resistors_SMD:R_0805_HandSoldering</footprint>
      <libsource lib="device" part="R"/>
      <sheetpath names="/HV power/" tstamps="/59EB6C7E/"/>
      <tstamp>59F052A1</tstamp>
    </comp>
    <comp ref="R9">
      <value>3.3k</value>
      <footprint>Resistors_SMD:R_0805_HandSoldering</footprint>
      <libsource lib="device" part="R"/>
      <sheetpath names="/HV power/" tstamps="/59EB6C7E/"/>
      <tstamp>59F052E7</tstamp>
    </comp>
    <comp ref="R10">
      <value>5.6k</value>
      <footprint>Resistors_SMD:R_0805_HandSoldering</footprint>
      <libsource lib="device" part="R"/>
      <sheetpath names="/HV power/" tstamps="/59EB6C7E/"/>
      <tstamp>59F05335</tstamp>
    </comp>
    <comp ref="RV2">
      <value>100k</value>
      <footprint>Potentiometers:Potentiometer_Trimmer_Bourns_3214G</footprint>
      <libsource lib="device" part="POT"/>
      <sheetpath names="/HV power/" tstamps="/59EB6C7E/"/>
      <tstamp>59F0539A</tstamp>
    </comp>
    <comp ref="C10">
      <value>10n</value>
      <footprint>Capacitors_SMD:C_0805_HandSoldering</footprint>
      <libsource lib="device" part="C"/>
      <sheetpath names="/HV power/" tstamps="/59EB6C7E/"/>
      <tstamp>59F055E8</tstamp>
    </comp>
    <comp ref="C11">
      <value>2.2u</value>
      <footprint>Capacitors_SMD:CP_Elec_8x10</footprint>
      <libsource lib="device" part="CP"/>
      <sheetpath names="/HV power/" tstamps="/59EB6C7E/"/>
      <tstamp>59F08F67</tstamp>
    </comp>
    <comp ref="R8">
      <value>165k</value>
      <footprint>Resistors_SMD:R_0805_HandSoldering</footprint>
      <libsource lib="device" part="R"/>
      <sheetpath names="/HV power/" tstamps="/59EB6C7E/"/>
      <tstamp>59FA26E2</tstamp>
    </comp>
    <comp ref="Q5">
      <value>IPN70R900P7SATMA1</value>
      <footprint>TO_SOT_Packages_SMD:SOT-223-3_TabPin2</footprint>
      <libsource lib="device" part="Q_NMOS_GDS"/>
      <sheetpath names="/HV power/" tstamps="/59EB6C7E/"/>
      <tstamp>59FD55A1</tstamp>
    </comp>
    <comp ref="Q4">
      <value>BC857W</value>
      <footprint>TO_SOT_Packages_SMD:SOT-323_SC-70_Handsoldering</footprint>
      <libsource lib="transistors" part="BC857W"/>
      <sheetpath names="/HV power/" tstamps="/59EB6C7E/"/>
      <tstamp>59FA03D4</tstamp>
    </comp>
    <comp ref="TP10">
      <value>TestPoint</value>
      <footprint>Measurement_Points:Measurement_Point_Round-SMD-Pad_Small</footprint>
      <libsource lib="components" part="TestPoint"/>
      <sheetpath names="/HV power/" tstamps="/59EB6C7E/"/>
      <tstamp>59FD2DBA</tstamp>
    </comp>
    <comp ref="TP11">
      <value>TestPoint</value>
      <footprint>Measurement_Points:Measurement_Point_Round-SMD-Pad_Small</footprint>
      <libsource lib="components" part="TestPoint"/>
      <sheetpath names="/HV power/" tstamps="/59EB6C7E/"/>
      <tstamp>59FD2F7C</tstamp>
    </comp>
    <comp ref="C9">
      <value>220u</value>
      <footprint>Capacitors_SMD:CP_Elec_8x10</footprint>
      <fields>
        <field name="Manufacturer">Nichicon</field>
        <field name="Manufacturer Part Number">UWT1E221MNL1GS</field>
        <field name="Notes">25V</field>
      </fields>
      <libsource lib="device" part="CP"/>
      <sheetpath names="/HV power/" tstamps="/59EB6C7E/"/>
      <tstamp>5A040D5C</tstamp>
    </comp>
    <comp ref="C12">
      <value>100n</value>
      <footprint>Capacitors_SMD:C_0805_HandSoldering</footprint>
      <libsource lib="device" part="C"/>
      <sheetpath names="/Real Time Clock/" tstamps="/59EB6D1A/"/>
      <tstamp>59F33790</tstamp>
    </comp>
    <comp ref="C13">
      <value>100n</value>
      <footprint>Capacitors_SMD:C_0805_HandSoldering</footprint>
      <libsource lib="device" part="C"/>
      <sheetpath names="/Real Time Clock/" tstamps="/59EB6D1A/"/>
      <tstamp>59F33B99</tstamp>
    </comp>
    <comp ref="BT1">
      <value>CR2032</value>
      <footprint>footprints:BATT_HOLDER</footprint>
      <libsource lib="device" part="Battery_Cell"/>
      <sheetpath names="/Real Time Clock/" tstamps="/59EB6D1A/"/>
      <tstamp>59F33D4C</tstamp>
    </comp>
    <comp ref="C14">
      <value>6p</value>
      <footprint>Capacitors_SMD:C_0805_HandSoldering</footprint>
      <libsource lib="device" part="C"/>
      <sheetpath names="/Real Time Clock/" tstamps="/59EB6D1A/"/>
      <tstamp>59F3404C</tstamp>
    </comp>
    <comp ref="C15">
      <value>6p</value>
      <footprint>Capacitors_SMD:C_0805_HandSoldering</footprint>
      <libsource lib="device" part="C"/>
      <sheetpath names="/Real Time Clock/" tstamps="/59EB6D1A/"/>
      <tstamp>59F3410B</tstamp>
    </comp>
    <comp ref="U3">
      <value>MCP7940N</value>
      <footprint>Housings_SOIC:SOIC-8_3.9x4.9mm_Pitch1.27mm</footprint>
      <libsource lib="microchip" part="MCP7940N"/>
      <sheetpath names="/Real Time Clock/" tstamps="/59EB6D1A/"/>
      <tstamp>59F11F1C</tstamp>
    </comp>
    <comp ref="Q6">
      <value>NTF5P03T3G</value>
      <footprint>TO_SOT_Packages_SMD:SOT-223-3_TabPin2</footprint>
      <libsource lib="device" part="Q_PMOS_GDS"/>
      <sheetpath names="/Real Time Clock/" tstamps="/59EB6D1A/"/>
      <tstamp>59FB17E2</tstamp>
    </comp>
    <comp ref="TP12">
      <value>TestPoint</value>
      <footprint>Measurement_Points:Measurement_Point_Round-SMD-Pad_Small</footprint>
      <libsource lib="components" part="TestPoint"/>
      <sheetpath names="/Real Time Clock/" tstamps="/59EB6D1A/"/>
      <tstamp>59FD9CB3</tstamp>
    </comp>
    <comp ref="TP13">
      <value>TestPoint</value>
      <footprint>Measurement_Points:Measurement_Point_Round-SMD-Pad_Small</footprint>
      <libsource lib="components" part="TestPoint"/>
      <sheetpath names="/Real Time Clock/" tstamps="/59EB6D1A/"/>
      <tstamp>59FD9CEE</tstamp>
    </comp>
    <comp ref="TP14">
      <value>TestPoint</value>
      <footprint>Measurement_Points:Measurement_Point_Round-SMD-Pad_Small</footprint>
      <libsource lib="components" part="TestPoint"/>
      <sheetpath names="/Real Time Clock/" tstamps="/59EB6D1A/"/>
      <tstamp>59FDA81C</tstamp>
    </comp>
    <comp ref="Y1">
      <value>32.768 kHz</value>
      <footprint>footprints:Citizen_CMR200T</footprint>
      <libsource lib="device" part="Crystal_GND3"/>
      <sheetpath names="/Real Time Clock/" tstamps="/59EB6D1A/"/>
      <tstamp>59FF12D4</tstamp>
    </comp>
    <comp ref="R11">
      <value>300</value>
      <footprint>Resistors_SMD:R_0805_HandSoldering</footprint>
      <libsource lib="device" part="R"/>
      <sheetpath names="/User I/O/" tstamps="/59EB6D2B/"/>
      <tstamp>59F39C0E</tstamp>
    </comp>
    <comp ref="D4">
      <value>LED</value>
      <footprint>LEDs:LED_0805_HandSoldering</footprint>
      <libsource lib="device" part="LED"/>
      <sheetpath names="/User I/O/" tstamps="/59EB6D2B/"/>
      <tstamp>59F39C6B</tstamp>
    </comp>
    <comp ref="SW1">
      <value>SW_Push</value>
      <footprint>footprints:SW_SMD</footprint>
      <libsource lib="switches" part="SW_Push"/>
      <sheetpath names="/User I/O/" tstamps="/59EB6D2B/"/>
      <tstamp>59F3B203</tstamp>
    </comp>
    <comp ref="SW2">
      <value>SW_Push</value>
      <footprint>footprints:SW_SMD</footprint>
      <libsource lib="switches" part="SW_Push"/>
      <sheetpath names="/User I/O/" tstamps="/59EB6D2B/"/>
      <tstamp>59F3B28F</tstamp>
    </comp>
    <comp ref="SW3">
      <value>SW_Push</value>
      <footprint>footprints:SW_SMD</footprint>
      <libsource lib="switches" part="SW_Push"/>
      <sheetpath names="/User I/O/" tstamps="/59EB6D2B/"/>
      <tstamp>59F3B2C1</tstamp>
    </comp>
    <comp ref="R12">
      <value>10k</value>
      <footprint>Resistors_SMD:R_0805_HandSoldering</footprint>
      <libsource lib="device" part="R"/>
      <sheetpath names="/User I/O/" tstamps="/59EB6D2B/"/>
      <tstamp>59F3BBFB</tstamp>
    </comp>
    <comp ref="R13">
      <value>10k</value>
      <footprint>Resistors_SMD:R_0805_HandSoldering</footprint>
      <libsource lib="device" part="R"/>
      <sheetpath names="/User I/O/" tstamps="/59EB6D2B/"/>
      <tstamp>59F3BC36</tstamp>
    </comp>
    <comp ref="C16">
      <value>100n</value>
      <footprint>Capacitors_SMD:C_0805_HandSoldering</footprint>
      <libsource lib="device" part="C"/>
      <sheetpath names="/User I/O/" tstamps="/59EB6D2B/"/>
      <tstamp>59F3CA4F</tstamp>
    </comp>
    <comp ref="C17">
      <value>100n</value>
      <footprint>Capacitors_SMD:C_0805_HandSoldering</footprint>
      <libsource lib="device" part="C"/>
      <sheetpath names="/User I/O/" tstamps="/59EB6D2B/"/>
      <tstamp>59F3CD46</tstamp>
    </comp>
    <comp ref="C18">
      <value>100n</value>
      <footprint>Capacitors_SMD:C_0805_HandSoldering</footprint>
      <libsource lib="device" part="C"/>
      <sheetpath names="/User I/O/" tstamps="/59EB6D2B/"/>
      <tstamp>59F3CDAA</tstamp>
    </comp>
    <comp ref="R14">
      <value>LDR</value>
      <footprint>Opto-Devices:Resistor_LDR_10x8.5_RM7.6</footprint>
      <libsource lib="opto" part="LDR03"/>
      <sheetpath names="/User I/O/" tstamps="/59EB6D2B/"/>
      <tstamp>59F8C32D</tstamp>
    </comp>
    <comp ref="RV3">
      <value>100k</value>
      <footprint>Potentiometers:Potentiometer_Trimmer_Bourns_3214G</footprint>
      <libsource lib="device" part="POT"/>
      <sheetpath names="/User I/O/" tstamps="/59EB6D2B/"/>
      <tstamp>59F8C5C6</tstamp>
    </comp>
    <comp ref="R15">
      <value>330k</value>
      <footprint>Resistors_SMD:R_0805_HandSoldering</footprint>
      <libsource lib="device" part="R"/>
      <sheetpath names="/User I/O/" tstamps="/59EB6D2B/"/>
      <tstamp>59F8D16D</tstamp>
    </comp>
    <comp ref="R16">
      <value>100k</value>
      <footprint>Resistors_SMD:R_0805_HandSoldering</footprint>
      <libsource lib="device" part="R"/>
      <sheetpath names="/User I/O/" tstamps="/59EB6D2B/"/>
      <tstamp>59F8D4FD</tstamp>
    </comp>
    <comp ref="TP15">
      <value>TestPoint</value>
      <footprint>Measurement_Points:Measurement_Point_Round-SMD-Pad_Small</footprint>
      <libsource lib="components" part="TestPoint"/>
      <sheetpath names="/User I/O/" tstamps="/59EB6D2B/"/>
      <tstamp>59FD684B</tstamp>
    </comp>
    <comp ref="TP16">
      <value>TestPoint</value>
      <footprint>Measurement_Points:Measurement_Point_Round-SMD-Pad_Small</footprint>
      <libsource lib="components" part="TestPoint"/>
      <sheetpath names="/User I/O/" tstamps="/59EB6D2B/"/>
      <tstamp>59FD6ACC</tstamp>
    </comp>
    <comp ref="C19">
      <value>220u</value>
      <footprint>Capacitors_SMD:CP_Elec_8x10</footprint>
      <fields>
        <field name="Manufacturer">Nichicon</field>
        <field name="Manufacturer Part Number">UWT1E221MNL1GS</field>
        <field name="Notes">25V</field>
      </fields>
      <libsource lib="device" part="CP"/>
      <sheetpath names="/Input power/" tstamps="/59EB6DF5/"/>
      <tstamp>59F3F952</tstamp>
    </comp>
    <comp ref="C20">
      <value>1u</value>
      <footprint>Capacitors_SMD:CP_Elec_8x10</footprint>
      <libsource lib="device" part="C"/>
      <sheetpath names="/Input power/" tstamps="/59EB6DF5/"/>
      <tstamp>59F3F9D6</tstamp>
    </comp>
    <comp ref="C21">
      <value>100n</value>
      <footprint>Capacitors_SMD:C_0805_HandSoldering</footprint>
      <libsource lib="device" part="C"/>
      <sheetpath names="/Input power/" tstamps="/59EB6DF5/"/>
      <tstamp>59F3FA21</tstamp>
    </comp>
    <comp ref="J1">
      <value>Power Jack</value>
      <footprint>Connectors:BARREL_JACK</footprint>
      <libsource lib="conn" part="Barrel_Jack"/>
      <sheetpath names="/Input power/" tstamps="/59EB6DF5/"/>
      <tstamp>59F3FAD7</tstamp>
    </comp>
    <comp ref="Q7">
      <value>NTF5P03T3G</value>
      <footprint>TO_SOT_Packages_SMD:SOT-223-3_TabPin2</footprint>
      <libsource lib="device" part="Q_PMOS_GDS"/>
      <sheetpath names="/Input power/" tstamps="/59EB6DF5/"/>
      <tstamp>59FB1DD6</tstamp>
    </comp>
    <comp ref="TP17">
      <value>TestPoint</value>
      <footprint>Measurement_Points:Measurement_Point_Round-SMD-Pad_Small</footprint>
      <libsource lib="components" part="TestPoint"/>
      <sheetpath names="/Input power/" tstamps="/59EB6DF5/"/>
      <tstamp>59FCF1DC</tstamp>
    </comp>
    <comp ref="J2">
      <value>Conn_01x03_Male</value>
      <footprint>Pin_Headers:Pin_Header_Straight_1x03_Pitch2.54mm</footprint>
      <libsource lib="conn" part="Conn_01x03_Male"/>
      <sheetpath names="/MCU ESP-12/" tstamps="/59EB6C93/"/>
      <tstamp>59F12416</tstamp>
    </comp>
    <comp ref="R18">
      <value>10k</value>
      <footprint>Resistors_SMD:R_0805_HandSoldering</footprint>
      <libsource lib="device" part="R"/>
      <sheetpath names="/MCU ESP-12/" tstamps="/59EB6C93/"/>
      <tstamp>59F12739</tstamp>
    </comp>
    <comp ref="R17">
      <value>10k</value>
      <footprint>Resistors_SMD:R_0805_HandSoldering</footprint>
      <libsource lib="device" part="R"/>
      <sheetpath names="/MCU ESP-12/" tstamps="/59EB6C93/"/>
      <tstamp>59F127F9</tstamp>
    </comp>
    <comp ref="SW4">
      <value>SW_Push</value>
      <footprint>footprints:SW_SMD</footprint>
      <libsource lib="switches" part="SW_Push"/>
      <sheetpath names="/MCU ESP-12/" tstamps="/59EB6C93/"/>
      <tstamp>59F13198</tstamp>
    </comp>
    <comp ref="C22">
      <value>100n</value>
      <footprint>Capacitors_SMD:C_0805_HandSoldering</footprint>
      <libsource lib="device" part="C"/>
      <sheetpath names="/MCU ESP-12/" tstamps="/59EB6C93/"/>
      <tstamp>59F13716</tstamp>
    </comp>
    <comp ref="C23">
      <value>10u</value>
      <footprint>Capacitors_SMD:CP_Elec_8x10</footprint>
      <libsource lib="device" part="CP"/>
      <sheetpath names="/MCU ESP-12/" tstamps="/59EB6C93/"/>
      <tstamp>59F13773</tstamp>
    </comp>
    <comp ref="R20">
      <value>10k</value>
      <footprint>Resistors_SMD:R_0805_HandSoldering</footprint>
      <libsource lib="device" part="R"/>
      <sheetpath names="/MCU ESP-12/" tstamps="/59EB6C93/"/>
      <tstamp>59F13F26</tstamp>
    </comp>
    <comp ref="R21">
      <value>10k</value>
      <footprint>Resistors_SMD:R_0805_HandSoldering</footprint>
      <libsource lib="device" part="R"/>
      <sheetpath names="/MCU ESP-12/" tstamps="/59EB6C93/"/>
      <tstamp>59F14123</tstamp>
    </comp>
    <comp ref="R22">
      <value>10k</value>
      <footprint>Resistors_SMD:R_0805_HandSoldering</footprint>
      <libsource lib="device" part="R"/>
      <sheetpath names="/MCU ESP-12/" tstamps="/59EB6C93/"/>
      <tstamp>59F141FE</tstamp>
    </comp>
    <comp ref="U4">
      <value>ESP-12</value>
      <footprint>footprints:ESP-12-SMD</footprint>
      <libsource lib="ESP8266" part="ESP-12"/>
      <sheetpath names="/MCU ESP-12/" tstamps="/59EB6C93/"/>
      <tstamp>59F0FCB4</tstamp>
    </comp>
    <comp ref="R19">
      <value>10k</value>
      <footprint>Resistors_SMD:R_0805_HandSoldering</footprint>
      <libsource lib="device" part="R"/>
      <sheetpath names="/MCU ESP-12/" tstamps="/59EB6C93/"/>
      <tstamp>59F16FEA</tstamp>
    </comp>
    <comp ref="R23">
      <value>10k</value>
      <footprint>Resistors_SMD:R_0805_HandSoldering</footprint>
      <libsource lib="device" part="R"/>
      <sheetpath names="/Nixie Tube drivers/" tstamps="/59EB6CE0/"/>
      <tstamp>59F22D74</tstamp>
    </comp>
    <comp ref="R26">
      <value>1k</value>
      <footprint>Resistors_SMD:R_0805_HandSoldering</footprint>
      <libsource lib="device" part="R"/>
      <sheetpath names="/Nixie Tube drivers/" tstamps="/59EB6CE0/"/>
      <tstamp>59F22D7A</tstamp>
    </comp>
    <comp ref="R24">
      <value>10k</value>
      <footprint>Resistors_SMD:R_0805_HandSoldering</footprint>
      <libsource lib="device" part="R"/>
      <sheetpath names="/Nixie Tube drivers/" tstamps="/59EB6CE0/"/>
      <tstamp>59F23796</tstamp>
    </comp>
    <comp ref="R27">
      <value>1k</value>
      <footprint>Resistors_SMD:R_0805_HandSoldering</footprint>
      <libsource lib="device" part="R"/>
      <sheetpath names="/Nixie Tube drivers/" tstamps="/59EB6CE0/"/>
      <tstamp>59F2379C</tstamp>
    </comp>
    <comp ref="R25">
      <value>10k</value>
      <footprint>Resistors_SMD:R_0805_HandSoldering</footprint>
      <libsource lib="device" part="R"/>
      <sheetpath names="/Nixie Tube drivers/" tstamps="/59EB6CE0/"/>
      <tstamp>59F2392C</tstamp>
    </comp>
    <comp ref="R28">
      <value>1k</value>
      <footprint>Resistors_SMD:R_0805_HandSoldering</footprint>
      <libsource lib="device" part="R"/>
      <sheetpath names="/Nixie Tube drivers/" tstamps="/59EB6CE0/"/>
      <tstamp>59F23932</tstamp>
    </comp>
    <comp ref="U5">
      <value>HV5522</value>
      <footprint>Housings_QFP:PQFP-44_10x10mm_Pitch0.8mm</footprint>
      <libsource lib="components" part="HV5522"/>
      <sheetpath names="/Nixie Tube drivers/" tstamps="/59EB6CE0/"/>
      <tstamp>59F67C28</tstamp>
    </comp>
    <comp ref="U6">
      <value>HV5522</value>
      <footprint>Housings_QFP:PQFP-44_10x10mm_Pitch0.8mm</footprint>
      <libsource lib="components" part="HV5522"/>
      <sheetpath names="/Nixie Tube drivers/" tstamps="/59EB6CE0/"/>
      <tstamp>59F6802D</tstamp>
    </comp>
    <comp ref="Q8">
      <value>BC847BW</value>
      <footprint>TO_SOT_Packages_SMD:SOT-323_SC-70_Handsoldering</footprint>
      <libsource lib="device" part="Q_NPN_BEC"/>
      <sheetpath names="/Nixie Tube drivers/" tstamps="/59EB6CE0/"/>
      <tstamp>59F9ECAB</tstamp>
    </comp>
    <comp ref="Q9">
      <value>BC847BW</value>
      <footprint>TO_SOT_Packages_SMD:SOT-323_SC-70_Handsoldering</footprint>
      <libsource lib="device" part="Q_NPN_BEC"/>
      <sheetpath names="/Nixie Tube drivers/" tstamps="/59EB6CE0/"/>
      <tstamp>59F9EED0</tstamp>
    </comp>
    <comp ref="Q10">
      <value>BC847BW</value>
      <footprint>TO_SOT_Packages_SMD:SOT-323_SC-70_Handsoldering</footprint>
      <libsource lib="device" part="Q_NPN_BEC"/>
      <sheetpath names="/Nixie Tube drivers/" tstamps="/59EB6CE0/"/>
      <tstamp>59F9EF29</tstamp>
    </comp>
    <comp ref="TP18">
      <value>TestPoint</value>
      <footprint>Measurement_Points:Measurement_Point_Round-SMD-Pad_Small</footprint>
      <libsource lib="components" part="TestPoint"/>
      <sheetpath names="/Nixie Tube drivers/" tstamps="/59EB6CE0/"/>
      <tstamp>59FDBB6A</tstamp>
    </comp>
    <comp ref="TP19">
      <value>TestPoint</value>
      <footprint>Measurement_Points:Measurement_Point_Round-SMD-Pad_Small</footprint>
      <libsource lib="components" part="TestPoint"/>
      <sheetpath names="/Nixie Tube drivers/" tstamps="/59EB6CE0/"/>
      <tstamp>59FDBE31</tstamp>
    </comp>
    <comp ref="TP20">
      <value>TestPoint</value>
      <footprint>Measurement_Points:Measurement_Point_Round-SMD-Pad_Small</footprint>
      <libsource lib="components" part="TestPoint"/>
      <sheetpath names="/Nixie Tube drivers/" tstamps="/59EB6CE0/"/>
      <tstamp>59FDC10A</tstamp>
    </comp>
    <comp ref="TP23">
      <value>TestPoint</value>
      <footprint>Measurement_Points:Measurement_Point_Round-SMD-Pad_Small</footprint>
      <libsource lib="components" part="TestPoint"/>
      <sheetpath names="/Nixie Tube drivers/" tstamps="/59EB6CE0/"/>
      <tstamp>59FDC721</tstamp>
    </comp>
    <comp ref="TP21">
      <value>TestPoint</value>
      <footprint>Measurement_Points:Measurement_Point_Round-SMD-Pad_Small</footprint>
      <libsource lib="components" part="TestPoint"/>
      <sheetpath names="/Nixie Tube drivers/" tstamps="/59EB6CE0/"/>
      <tstamp>59FDCA68</tstamp>
    </comp>
    <comp ref="TP22">
      <value>TestPoint</value>
      <footprint>Measurement_Points:Measurement_Point_Round-SMD-Pad_Small</footprint>
      <libsource lib="components" part="TestPoint"/>
      <sheetpath names="/Nixie Tube drivers/" tstamps="/59EB6CE0/"/>
      <tstamp>59FDCE2D</tstamp>
    </comp>
    <comp ref="TP24">
      <value>TestPoint</value>
      <footprint>Measurement_Points:Measurement_Point_Round-SMD-Pad_Small</footprint>
      <libsource lib="components" part="TestPoint"/>
      <sheetpath names="/Nixie Tube drivers/" tstamps="/59EB6CE0/"/>
      <tstamp>59FDDFF3</tstamp>
    </comp>
    <comp ref="TP25">
      <value>TestPoint</value>
      <footprint>Measurement_Points:Measurement_Point_Round-SMD-Pad_Small</footprint>
      <libsource lib="components" part="TestPoint"/>
      <sheetpath names="/Nixie Tube drivers/" tstamps="/59EB6CE0/"/>
      <tstamp>59FE61EE</tstamp>
    </comp>
    <comp ref="TP26">
      <value>TestPoint</value>
      <footprint>Measurement_Points:Measurement_Point_Round-SMD-Pad_Small</footprint>
      <libsource lib="components" part="TestPoint"/>
      <sheetpath names="/Nixie Tube drivers/" tstamps="/59EB6CE0/"/>
      <tstamp>59FE63D1</tstamp>
    </comp>
    <comp ref="C24">
      <value>100n</value>
      <footprint>Capacitors_SMD:C_0805_HandSoldering</footprint>
      <libsource lib="device" part="C"/>
      <sheetpath names="/Nixie Tube drivers/" tstamps="/59EB6CE0/"/>
      <tstamp>5A0462F1</tstamp>
    </comp>
    <comp ref="C25">
      <value>100n</value>
      <footprint>Capacitors_SMD:C_0805_HandSoldering</footprint>
      <libsource lib="device" part="C"/>
      <sheetpath names="/Nixie Tube drivers/" tstamps="/59EB6CE0/"/>
      <tstamp>5A046A31</tstamp>
    </comp>
    <comp ref="R47">
      <value>0R</value>
      <footprint>Resistors_SMD:R_0805_HandSoldering</footprint>
      <libsource lib="device" part="R"/>
      <sheetpath names="/Nixie Tube drivers/" tstamps="/59EB6CE0/"/>
      <tstamp>5A016C5D</tstamp>
    </comp>
    <comp ref="R48">
      <value>0R</value>
      <footprint>Resistors_SMD:R_0805_HandSoldering</footprint>
      <libsource lib="device" part="R"/>
      <sheetpath names="/Nixie Tube drivers/" tstamps="/59EB6CE0/"/>
      <tstamp>5A018091</tstamp>
    </comp>
    <comp ref="R49">
      <value>0R</value>
      <footprint>Resistors_SMD:R_0805_HandSoldering</footprint>
      <libsource lib="device" part="R"/>
      <sheetpath names="/Nixie Tube drivers/" tstamps="/59EB6CE0/"/>
      <tstamp>5A0180F1</tstamp>
    </comp>
    <comp ref="R50">
      <value>0R</value>
      <footprint>Resistors_SMD:R_0805_HandSoldering</footprint>
      <libsource lib="device" part="R"/>
      <sheetpath names="/Nixie Tube drivers/" tstamps="/59EB6CE0/"/>
      <tstamp>5A0189E0</tstamp>
    </comp>
    <comp ref="R38">
      <value>68k</value>
      <footprint>Resistors_SMD:R_0805_HandSoldering</footprint>
      <libsource lib="device" part="R"/>
      <sheetpath names="/Nixie Tubes/" tstamps="/59EB6D02/"/>
      <tstamp>59F84EDC</tstamp>
    </comp>
    <comp ref="R33">
      <value>68k</value>
      <footprint>Resistors_SMD:R_0805_HandSoldering</footprint>
      <libsource lib="device" part="R"/>
      <sheetpath names="/Nixie Tubes/" tstamps="/59EB6D02/"/>
      <tstamp>59F870B1</tstamp>
    </comp>
    <comp ref="NE1">
      <value>Lamp_Neon</value>
      <footprint>footprints:NE-2</footprint>
      <libsource lib="device" part="Lamp_Neon"/>
      <sheetpath names="/Nixie Tubes/" tstamps="/59EB6D02/"/>
      <tstamp>59F88934</tstamp>
    </comp>
    <comp ref="N1">
      <value>IN-14</value>
      <footprint>footprints:IN-14</footprint>
      <libsource lib="components" part="IN-14"/>
      <sheetpath names="/Nixie Tubes/" tstamps="/59EB6D02/"/>
      <tstamp>59F88C4C</tstamp>
    </comp>
    <comp ref="N3">
      <value>IN-14</value>
      <footprint>footprints:IN-14</footprint>
      <libsource lib="components" part="IN-14"/>
      <sheetpath names="/Nixie Tubes/" tstamps="/59EB6D02/"/>
      <tstamp>59F88D44</tstamp>
    </comp>
    <comp ref="N5">
      <value>IN-14</value>
      <footprint>footprints:IN-14</footprint>
      <libsource lib="components" part="IN-14"/>
      <sheetpath names="/Nixie Tubes/" tstamps="/59EB6D02/"/>
      <tstamp>59F88DBA</tstamp>
    </comp>
    <comp ref="N2">
      <value>IN-14</value>
      <footprint>footprints:IN-14</footprint>
      <libsource lib="components" part="IN-14"/>
      <sheetpath names="/Nixie Tubes/" tstamps="/59EB6D02/"/>
      <tstamp>59F88E9C</tstamp>
    </comp>
    <comp ref="N4">
      <value>IN-14</value>
      <footprint>footprints:IN-14</footprint>
      <libsource lib="components" part="IN-14"/>
      <sheetpath names="/Nixie Tubes/" tstamps="/59EB6D02/"/>
      <tstamp>59F88F17</tstamp>
    </comp>
    <comp ref="N6">
      <value>IN-14</value>
      <footprint>footprints:IN-14</footprint>
      <libsource lib="components" part="IN-14"/>
      <sheetpath names="/Nixie Tubes/" tstamps="/59EB6D02/"/>
      <tstamp>59F88F8B</tstamp>
    </comp>
    <comp ref="NE2">
      <value>Lamp_Neon</value>
      <footprint>footprints:NE-2</footprint>
      <libsource lib="device" part="Lamp_Neon"/>
      <sheetpath names="/Nixie Tubes/" tstamps="/59EB6D02/"/>
      <tstamp>59F89760</tstamp>
    </comp>
    <comp ref="R29">
      <value>5k</value>
      <footprint>Resistors_SMD:R_0805_HandSoldering</footprint>
      <libsource lib="device" part="R"/>
      <sheetpath names="/Nixie Tubes/" tstamps="/59EB6D02/"/>
      <tstamp>59FA45E5</tstamp>
    </comp>
    <comp ref="R30">
      <value>5k</value>
      <footprint>Resistors_SMD:R_0805_HandSoldering</footprint>
      <libsource lib="device" part="R"/>
      <sheetpath names="/Nixie Tubes/" tstamps="/59EB6D02/"/>
      <tstamp>59FA47A7</tstamp>
    </comp>
    <comp ref="R35">
      <value>5k</value>
      <footprint>Resistors_SMD:R_0805_HandSoldering</footprint>
      <libsource lib="device" part="R"/>
      <sheetpath names="/Nixie Tubes/" tstamps="/59EB6D02/"/>
      <tstamp>59FA47F6</tstamp>
    </comp>
    <comp ref="R34">
      <value>5k</value>
      <footprint>Resistors_SMD:R_0805_HandSoldering</footprint>
      <libsource lib="device" part="R"/>
      <sheetpath names="/Nixie Tubes/" tstamps="/59EB6D02/"/>
      <tstamp>59FA489A</tstamp>
    </comp>
    <comp ref="R40">
      <value>5k</value>
      <footprint>Resistors_SMD:R_0805_HandSoldering</footprint>
      <libsource lib="device" part="R"/>
      <sheetpath names="/Nixie Tubes/" tstamps="/59EB6D02/"/>
      <tstamp>59FA49D5</tstamp>
    </comp>
    <comp ref="R39">
      <value>5k</value>
      <footprint>Resistors_SMD:R_0805_HandSoldering</footprint>
      <libsource lib="device" part="R"/>
      <sheetpath names="/Nixie Tubes/" tstamps="/59EB6D02/"/>
      <tstamp>59FA4A41</tstamp>
    </comp>
    <comp ref="R32">
      <value>5k</value>
      <footprint>Resistors_SMD:R_0805_HandSoldering</footprint>
      <libsource lib="device" part="R"/>
      <sheetpath names="/Nixie Tubes/" tstamps="/59EB6D02/"/>
      <tstamp>59FA51A5</tstamp>
    </comp>
    <comp ref="R31">
      <value>5k</value>
      <footprint>Resistors_SMD:R_0805_HandSoldering</footprint>
      <libsource lib="device" part="R"/>
      <sheetpath names="/Nixie Tubes/" tstamps="/59EB6D02/"/>
      <tstamp>59FA5446</tstamp>
    </comp>
    <comp ref="R37">
      <value>5k</value>
      <footprint>Resistors_SMD:R_0805_HandSoldering</footprint>
      <libsource lib="device" part="R"/>
      <sheetpath names="/Nixie Tubes/" tstamps="/59EB6D02/"/>
      <tstamp>59FA56D6</tstamp>
    </comp>
    <comp ref="R36">
      <value>5k</value>
      <footprint>Resistors_SMD:R_0805_HandSoldering</footprint>
      <libsource lib="device" part="R"/>
      <sheetpath names="/Nixie Tubes/" tstamps="/59EB6D02/"/>
      <tstamp>59FA5947</tstamp>
    </comp>
    <comp ref="R42">
      <value>5k</value>
      <footprint>Resistors_SMD:R_0805_HandSoldering</footprint>
      <libsource lib="device" part="R"/>
      <sheetpath names="/Nixie Tubes/" tstamps="/59EB6D02/"/>
      <tstamp>59FA5DBB</tstamp>
    </comp>
    <comp ref="R41">
      <value>5k</value>
      <footprint>Resistors_SMD:R_0805_HandSoldering</footprint>
      <libsource lib="device" part="R"/>
      <sheetpath names="/Nixie Tubes/" tstamps="/59EB6D02/"/>
      <tstamp>59FA5F84</tstamp>
    </comp>
    <comp ref="R44">
      <value>100k</value>
      <footprint>Resistors_SMD:R_0805_HandSoldering</footprint>
      <libsource lib="device" part="R"/>
      <sheetpath names="/Nixie Tubes/" tstamps="/59EB6D02/"/>
      <tstamp>59FA7A9B</tstamp>
    </comp>
    <comp ref="R46">
      <value>100k</value>
      <footprint>Resistors_SMD:R_0805_HandSoldering</footprint>
      <libsource lib="device" part="R"/>
      <sheetpath names="/Nixie Tubes/" tstamps="/59EB6D02/"/>
      <tstamp>59FA7B7F</tstamp>
    </comp>
    <comp ref="R45">
      <value>100k</value>
      <footprint>Resistors_SMD:R_0805_HandSoldering</footprint>
      <libsource lib="device" part="R"/>
      <sheetpath names="/Nixie Tubes/" tstamps="/59EB6D02/"/>
      <tstamp>59FA7BF3</tstamp>
    </comp>
    <comp ref="R43">
      <value>100k</value>
      <footprint>Resistors_SMD:R_0805_HandSoldering</footprint>
      <libsource lib="device" part="R"/>
      <sheetpath names="/Nixie Tubes/" tstamps="/59EB6D02/"/>
      <tstamp>59FA7C6A</tstamp>
    </comp>
    <comp ref="LED1">
      <value>WS2812</value>
      <footprint>LEDs:LED_WS2812-PLCC6</footprint>
      <libsource lib="Worldsemi" part="WS2812"/>
      <sheetpath names="/Programmable LEDs/" tstamps="/59FFB7E0/"/>
      <tstamp>5A0045B7</tstamp>
    </comp>
    <comp ref="LED2">
      <value>WS2812</value>
      <footprint>LEDs:LED_WS2812-PLCC6</footprint>
      <libsource lib="Worldsemi" part="WS2812"/>
      <sheetpath names="/Programmable LEDs/" tstamps="/59FFB7E0/"/>
      <tstamp>5A0046A0</tstamp>
    </comp>
    <comp ref="LED3">
      <value>WS2812</value>
      <footprint>LEDs:LED_WS2812-PLCC6</footprint>
      <libsource lib="Worldsemi" part="WS2812"/>
      <sheetpath names="/Programmable LEDs/" tstamps="/59FFB7E0/"/>
      <tstamp>5A0048F0</tstamp>
    </comp>
    <comp ref="LED4">
      <value>WS2812</value>
      <footprint>LEDs:LED_WS2812-PLCC6</footprint>
      <libsource lib="Worldsemi" part="WS2812"/>
      <sheetpath names="/Programmable LEDs/" tstamps="/59FFB7E0/"/>
      <tstamp>5A0048F6</tstamp>
    </comp>
    <comp ref="C6">
      <value>100n</value>
      <footprint>Capacitors_SMD:C_0805_HandSoldering</footprint>
      <libsource lib="device" part="C"/>
      <sheetpath names="/Programmable LEDs/" tstamps="/59FFB7E0/"/>
      <tstamp>5A006863</tstamp>
    </comp>
    <comp ref="C26">
      <value>100n</value>
      <footprint>Capacitors_SMD:C_0805_HandSoldering</footprint>
      <libsource lib="device" part="C"/>
      <sheetpath names="/Programmable LEDs/" tstamps="/59FFB7E0/"/>
      <tstamp>5A0068AE</tstamp>
    </comp>
    <comp ref="LED5">
      <value>WS2812</value>
      <footprint>LEDs:LED_WS2812-PLCC6</footprint>
      <libsource lib="Worldsemi" part="WS2812"/>
      <sheetpath names="/Programmable LEDs/" tstamps="/59FFB7E0/"/>
      <tstamp>5A009456</tstamp>
    </comp>
    <comp ref="LED6">
      <value>WS2812</value>
      <footprint>LEDs:LED_WS2812-PLCC6</footprint>
      <libsource lib="Worldsemi" part="WS2812"/>
      <sheetpath names="/Programmable LEDs/" tstamps="/59FFB7E0/"/>
      <tstamp>5A00945C</tstamp>
    </comp>
    <comp ref="R4">
      <value>10k</value>
      <footprint>Resistors_SMD:R_0805_HandSoldering</footprint>
      <libsource lib="device" part="R"/>
      <sheetpath names="/Programmable LEDs/" tstamps="/59FFB7E0/"/>
      <tstamp>5A00D1BF</tstamp>
    </comp>
    <comp ref="R5">
      <value>1k</value>
      <footprint>Resistors_SMD:R_0805_HandSoldering</footprint>
      <libsource lib="device" part="R"/>
      <sheetpath names="/Programmable LEDs/" tstamps="/59FFB7E0/"/>
      <tstamp>5A00D1C6</tstamp>
    </comp>
    <comp ref="Q11">
      <value>BC847BW</value>
      <footprint>TO_SOT_Packages_SMD:SOT-323_SC-70_Handsoldering</footprint>
      <libsource lib="device" part="Q_NPN_BEC"/>
      <sheetpath names="/Programmable LEDs/" tstamps="/59FFB7E0/"/>
      <tstamp>5A00D1E2</tstamp>
    </comp>
    <comp ref="TP28">
      <value>TestPoint</value>
      <footprint>Measurement_Points:Measurement_Point_Round-SMD-Pad_Small</footprint>
      <libsource lib="components" part="TestPoint"/>
      <sheetpath names="/Programmable LEDs/" tstamps="/59FFB7E0/"/>
      <tstamp>5A00D1F2</tstamp>
    </comp>
    <comp ref="TP27">
      <value>TestPoint</value>
      <footprint>Measurement_Points:Measurement_Point_Round-SMD-Pad_Small</footprint>
      <libsource lib="components" part="TestPoint"/>
      <sheetpath names="/Programmable LEDs/" tstamps="/59FFB7E0/"/>
      <tstamp>5A00D1E9</tstamp>
    </comp>
    <comp ref="TP29">
      <value>TestPoint</value>
      <footprint>Measurement_Points:Measurement_Point_Round-SMD-Pad_Small</footprint>
      <libsource lib="components" part="TestPoint"/>
      <sheetpath names="/Programmable LEDs/" tstamps="/59FFB7E0/"/>
      <tstamp>5A018383</tstamp>
    </comp>
    <comp ref="U7">
      <value>AZ1117-3.3</value>
      <footprint>TO_SOT_Packages_SMD:SOT-223-3_TabPin2</footprint>
      <libsource lib="regul" part="AZ1117-3.3"/>
      <sheetpath names="/Programmable LEDs/" tstamps="/59FFB7E0/"/>
      <tstamp>59FF76B4</tstamp>
    </comp>
  </components>
  <libparts>
    <libpart lib="regul" part="AZ1117-1.2">
      <aliases>
        <alias>AZ1117-1.5</alias>
        <alias>AZ1117-1.8</alias>
        <alias>AZ1117-2.5</alias>
        <alias>AZ1117-2.85</alias>
        <alias>AZ1117-3.3</alias>
        <alias>AZ1117-5.0</alias>
      </aliases>
      <description>1A 20V Fixed LDO Linear Regulator, 1.2V, SOT-89/SOT-223/TO-220/TO-252/TO-263</description>
      <docs>https://www.diodes.com/assets/Datasheets/AZ1117.pdf</docs>
      <footprints>
        <fp>SOT?223*</fp>
        <fp>SOT?89*</fp>
        <fp>TO?220*</fp>
        <fp>TO?252*</fp>
        <fp>TO?263*</fp>
      </footprints>
      <fields>
        <field name="Reference">U</field>
        <field name="Value">AZ1117-1.2</field>
      </fields>
      <pins>
        <pin num="1" name="GND" type="power_in"/>
        <pin num="2" name="VO" type="power_out"/>
        <pin num="3" name="VI" type="power_in"/>
      </pins>
    </libpart>
    <libpart lib="transistors" part="BC807W">
      <aliases>
        <alias>BC808W</alias>
        <alias>BC856W</alias>
        <alias>BC857W</alias>
        <alias>BC858W</alias>
        <alias>BC859W</alias>
        <alias>BC860W</alias>
      </aliases>
      <description>45V Vce, 0.8A Ic, PNP, SOT-323</description>
      <docs>http://www.fairchildsemi.com/ds/BC/BC807.pdf</docs>
      <footprints>
        <fp>SOT?323*</fp>
      </footprints>
      <fields>
        <field name="Reference">Q</field>
        <field name="Value">BC807W</field>
        <field name="Footprint">TO_SOT_Packages_SMD:SOT-323</field>
      </fields>
      <pins>
        <pin num="1" name="B" type="input"/>
        <pin num="2" name="E" type="passive"/>
        <pin num="3" name="C" type="passive"/>
      </pins>
    </libpart>
    <libpart lib="conn" part="Barrel_Jack">
      <aliases>
        <alias>Jack-DC</alias>
      </aliases>
      <description>DCBarrel Jack</description>
      <docs>~</docs>
      <fields>
        <field name="Reference">J</field>
        <field name="Value">Barrel_Jack</field>
      </fields>
      <pins>
        <pin num="1" name="~" type="passive"/>
        <pin num="2" name="~" type="passive"/>
        <pin num="3" name="~" type="passive"/>
      </pins>
    </libpart>
    <libpart lib="device" part="Battery_Cell">
      <description>single battery cell</description>
      <fields>
        <field name="Reference">BT</field>
        <field name="Value">Battery_Cell</field>
      </fields>
      <pins>
        <pin num="1" name="+" type="passive"/>
        <pin num="2" name="-" type="passive"/>
      </pins>
    </libpart>
    <libpart lib="device" part="C">
      <description>Unpolarized capacitor</description>
      <footprints>
        <fp>C_*</fp>
      </footprints>
      <fields>
        <field name="Reference">C</field>
        <field name="Value">C</field>
      </fields>
      <pins>
        <pin num="1" name="~" type="passive"/>
        <pin num="2" name="~" type="passive"/>
      </pins>
    </libpart>
    <libpart lib="device" part="CP">
      <description>Polarised capacitor</description>
      <footprints>
        <fp>CP_*</fp>
      </footprints>
      <fields>
        <field name="Reference">C</field>
        <field name="Value">CP</field>
      </fields>
      <pins>
        <pin num="1" name="~" type="passive"/>
        <pin num="2" name="~" type="passive"/>
      </pins>
    </libpart>
    <libpart lib="conn" part="Conn_01x03_Male">
      <description>Generic connector, single row, 01x03</description>
      <docs>~</docs>
      <footprints>
        <fp>Connector*:*_??x*mm*</fp>
        <fp>Connector*:*1x??x*mm*</fp>
        <fp>Pin?Header?Straight?1X*</fp>
        <fp>Pin?Header?Angled?1X*</fp>
      </footprints>
      <fields>
        <field name="Reference">J</field>
        <field name="Value">Conn_01x03_Male</field>
      </fields>
      <pins>
        <pin num="1" name="Pin_1" type="passive"/>
        <pin num="2" name="Pin_2" type="passive"/>
        <pin num="3" name="Pin_3" type="passive"/>
      </pins>
    </libpart>
    <libpart lib="device" part="Crystal_GND3">
      <description>Three pin crystal (GND on pin 3), e.g. in SMD package</description>
      <footprints>
        <fp>Crystal*</fp>
      </footprints>
      <fields>
        <field name="Reference">Y</field>
        <field name="Value">Crystal_GND3</field>
      </fields>
      <pins>
        <pin num="1" name="1" type="passive"/>
        <pin num="2" name="2" type="passive"/>
        <pin num="3" name="3" type="passive"/>
      </pins>
    </libpart>
    <libpart lib="device" part="D">
      <description>Diode</description>
      <footprints>
        <fp>TO-???*</fp>
        <fp>*SingleDiode</fp>
        <fp>*_Diode_*</fp>
        <fp>*SingleDiode*</fp>
        <fp>D_*</fp>
      </footprints>
      <fields>
        <field name="Reference">D</field>
        <field name="Value">D</field>
      </fields>
      <pins>
        <pin num="1" name="K" type="passive"/>
        <pin num="2" name="A" type="passive"/>
      </pins>
    </libpart>
    <libpart lib="ESP8266" part="ESP-12">
      <aliases>
        <alias>ESP-07v2</alias>
      </aliases>
      <description>ESP8266 ESP-12 module, 16 pins, 2mm, PCB antenna</description>
      <docs>http://l0l.org.uk/2014/12/esp8266-modules-hardware-guide-gotta-catch-em-all/</docs>
      <footprints>
        <fp>ESP-07*</fp>
        <fp>ESP-12*</fp>
      </footprints>
      <fields>
        <field name="Reference">U</field>
        <field name="Value">ESP-12</field>
      </fields>
      <pins>
        <pin num="1" name="REST" type="input"/>
        <pin num="2" name="ADC" type="passive"/>
        <pin num="3" name="CH_PD" type="input"/>
        <pin num="4" name="GPIO16" type="BiDi"/>
        <pin num="5" name="GPIO14" type="BiDi"/>
        <pin num="6" name="GPIO12" type="BiDi"/>
        <pin num="7" name="GPIO13" type="BiDi"/>
        <pin num="8" name="VCC" type="power_in"/>
        <pin num="9" name="GND" type="power_in"/>
        <pin num="10" name="GPIO15" type="BiDi"/>
        <pin num="11" name="GPIO2" type="BiDi"/>
        <pin num="12" name="GPIO0" type="BiDi"/>
        <pin num="13" name="GPIO4" type="BiDi"/>
        <pin num="14" name="GPIO5" type="BiDi"/>
        <pin num="15" name="RXD" type="input"/>
        <pin num="16" name="TXD" type="output"/>
      </pins>
    </libpart>
    <libpart lib="components" part="Fiducial">
      <description>Fiducial point</description>
      <fields>
        <field name="Reference">F</field>
        <field name="Value">Fiducial</field>
      </fields>
    </libpart>
    <libpart lib="components" part="HV5522">
      <description>High Voltage 32-channel serial to parallel converter with Open Drain outputs</description>
      <docs>https://www.futurel.bg/datasheets/4/HV5522.pdf</docs>
      <fields>
        <field name="Reference">U</field>
        <field name="Value">HV5522</field>
      </fields>
      <pins>
        <pin num="1" name="HV_16" type="openCol"/>
        <pin num="2" name="HV_17" type="openCol"/>
        <pin num="3" name="HV_18" type="openCol"/>
        <pin num="4" name="HV_19" type="openCol"/>
        <pin num="5" name="HV_20" type="openCol"/>
        <pin num="6" name="HV_21" type="openCol"/>
        <pin num="7" name="HV_22" type="openCol"/>
        <pin num="8" name="HV_23" type="openCol"/>
        <pin num="9" name="HV_24" type="openCol"/>
        <pin num="10" name="HV_25" type="openCol"/>
        <pin num="11" name="HV_26" type="openCol"/>
        <pin num="12" name="HV_27" type="openCol"/>
        <pin num="13" name="HV_28" type="openCol"/>
        <pin num="14" name="HV_29" type="openCol"/>
        <pin num="15" name="HV_30" type="openCol"/>
        <pin num="16" name="HV_31" type="openCol"/>
        <pin num="17" name="HV_32" type="openCol"/>
        <pin num="18" name="Data_Out" type="output"/>
        <pin num="19" name="NC" type="NotConnected"/>
        <pin num="20" name="NC" type="NotConnected"/>
        <pin num="21" name="NC" type="NotConnected"/>
        <pin num="22" name="~Polarity" type="input"/>
        <pin num="23" name="CLK" type="input"/>
        <pin num="24" name="VSS" type="power_in"/>
        <pin num="25" name="VDD" type="power_in"/>
        <pin num="26" name="~Latch_Enable" type="input"/>
        <pin num="27" name="Data_In" type="input"/>
        <pin num="28" name="~Blank" type="input"/>
        <pin num="29" name="NC" type="NotConnected"/>
        <pin num="30" name="HV_1" type="openCol"/>
        <pin num="31" name="HV_2" type="openCol"/>
        <pin num="32" name="HV_3" type="openCol"/>
        <pin num="33" name="HV_4" type="openCol"/>
        <pin num="34" name="HV_5" type="openCol"/>
        <pin num="35" name="HV_6" type="openCol"/>
        <pin num="36" name="HV_7" type="openCol"/>
        <pin num="37" name="HV_8" type="openCol"/>
        <pin num="38" name="HV_9" type="openCol"/>
        <pin num="39" name="HV_10" type="openCol"/>
        <pin num="40" name="HV_11" type="openCol"/>
        <pin num="41" name="HV_12" type="openCol"/>
        <pin num="42" name="HV_13" type="openCol"/>
        <pin num="43" name="HV_14" type="openCol"/>
        <pin num="44" name="HV_15" type="openCol"/>
      </pins>
    </libpart>
    <libpart lib="components" part="IN-14">
      <description>Russian 10 digit Nixie tube with two decimal points</description>
      <fields>
        <field name="Reference">N</field>
        <field name="Value">IN-14</field>
      </fields>
      <pins>
        <pin num="1" name="Anode" type="input"/>
        <pin num="2" name="C_DP_L" type="input"/>
        <pin num="3" name="C_1" type="input"/>
        <pin num="4" name="C_2" type="input"/>
        <pin num="5" name="C_3" type="input"/>
        <pin num="6" name="C_4" type="input"/>
        <pin num="7" name="C_5" type="input"/>
        <pin num="8" name="C_6" type="input"/>
        <pin num="9" name="C_7" type="input"/>
        <pin num="10" name="C_8" type="input"/>
        <pin num="11" name="C_9" type="input"/>
        <pin num="12" name="C_0" type="input"/>
        <pin num="13" name="C_DP_R" type="input"/>
      </pins>
    </libpart>
    <libpart lib="device" part="L">
      <description>Inductor</description>
      <footprints>
        <fp>Choke_*</fp>
        <fp>*Coil*</fp>
        <fp>Inductor_*</fp>
        <fp>L_*</fp>
      </footprints>
      <fields>
        <field name="Reference">L</field>
        <field name="Value">L</field>
      </fields>
      <pins>
        <pin num="1" name="1" type="passive"/>
        <pin num="2" name="2" type="passive"/>
      </pins>
    </libpart>
    <libpart lib="opto" part="LDR03">
      <description>light dependent resistor</description>
      <docs>http://www.elektronica-componenten.nl/WebRoot/StoreNL/Shops/61422969/54F1/BA0C/C664/31B9/2173/C0A8/2AB9/2AEF/LDR03IMP.pdf</docs>
      <footprints>
        <fp>Resistor*LDR*10x8.5*RM7.6*</fp>
      </footprints>
      <fields>
        <field name="Reference">R</field>
        <field name="Value">LDR03</field>
        <field name="Footprint">Opto-Devices:Resistor_LDR_10x8.5_RM7.6</field>
      </fields>
      <pins>
        <pin num="1" name="~" type="passive"/>
        <pin num="2" name="~" type="passive"/>
      </pins>
    </libpart>
    <libpart lib="device" part="LED">
      <description>LED generic</description>
      <footprints>
        <fp>LED*</fp>
      </footprints>
      <fields>
        <field name="Reference">D</field>
        <field name="Value">LED</field>
      </fields>
      <pins>
        <pin num="1" name="K" type="passive"/>
        <pin num="2" name="A" type="passive"/>
      </pins>
    </libpart>
    <libpart lib="device" part="Lamp_Neon">
      <description>neon lamp</description>
      <fields>
        <field name="Reference">NE</field>
        <field name="Value">Lamp_Neon</field>
      </fields>
      <pins>
        <pin num="1" name="~" type="passive"/>
        <pin num="2" name="~" type="passive"/>
      </pins>
    </libpart>
    <libpart lib="dc-dc" part="MC34063">
      <description>1.5A step up/down/inverting switching regulator</description>
      <docs>http://www.onsemi.com/pub_link/Collateral/MC34063A-D.PDF</docs>
      <footprints>
        <fp>DIP*W7.62mm*</fp>
        <fp>SOIC*3.9x4.9mm*Pitch1.27mm*</fp>
        <fp>DFN*</fp>
      </footprints>
      <fields>
        <field name="Reference">U</field>
        <field name="Value">MC34063</field>
      </fields>
      <pins>
        <pin num="1" name="SwC" type="passive"/>
        <pin num="2" name="SwE" type="passive"/>
        <pin num="3" name="TC" type="input"/>
        <pin num="4" name="GND" type="power_in"/>
        <pin num="5" name="Vfb" type="input"/>
        <pin num="6" name="Vin(VCC)" type="power_in"/>
        <pin num="7" name="Ipk" type="input"/>
        <pin num="8" name="DC" type="passive"/>
      </pins>
    </libpart>
    <libpart lib="microchip" part="MCP7940N">
      <description>Real-Time Clock, I2C, Battery Backup</description>
      <docs>http://ww1.microchip.com/downloads/en/DeviceDoc/20005010F.pdf</docs>
      <footprints>
        <fp>SOIC*3.9x4.9mm*Pitch1.27mm*</fp>
        <fp>TSSOP*4.4x3mm*Pitch0.65mm*</fp>
        <fp>MSOP*3x3mm*Pitch0.65mm*</fp>
        <fp>DFN*3x2mm*Pitch0.5mm*</fp>
        <fp>DIP*W7.62mm*</fp>
      </footprints>
      <fields>
        <field name="Reference">U</field>
        <field name="Value">MCP7940N</field>
      </fields>
      <pins>
        <pin num="1" name="X1" type="input"/>
        <pin num="2" name="X2" type="output"/>
        <pin num="3" name="VBAT" type="power_in"/>
        <pin num="4" name="VSS" type="power_in"/>
        <pin num="5" name="SDA" type="BiDi"/>
        <pin num="6" name="SCL" type="input"/>
        <pin num="7" name="MFP" type="openCol"/>
        <pin num="8" name="VCC" type="power_in"/>
      </pins>
    </libpart>
    <libpart lib="mechanical" part="Mounting_Hole_PAD">
      <description>Mounting Hole with connection</description>
      <footprints>
        <fp>Mounting?Hole*</fp>
        <fp>Hole*</fp>
      </footprints>
      <fields>
        <field name="Reference">MK</field>
        <field name="Value">Mounting_Hole_PAD</field>
      </fields>
      <pins>
        <pin num="1" name="1" type="input"/>
      </pins>
    </libpart>
    <libpart lib="device" part="POT">
      <description>Potentiometer</description>
      <footprints>
        <fp>Potentiometer*</fp>
      </footprints>
      <fields>
        <field name="Reference">RV</field>
        <field name="Value">POT</field>
      </fields>
      <pins>
        <pin num="1" name="1" type="passive"/>
        <pin num="2" name="2" type="passive"/>
        <pin num="3" name="3" type="passive"/>
      </pins>
    </libpart>
    <libpart lib="device" part="Q_NMOS_GDS">
      <description>Transistor N-MOSFET with substrate diode (general)</description>
      <fields>
        <field name="Reference">Q</field>
        <field name="Value">Q_NMOS_GDS</field>
      </fields>
      <pins>
        <pin num="1" name="G" type="input"/>
        <pin num="2" name="D" type="passive"/>
        <pin num="3" name="S" type="passive"/>
      </pins>
    </libpart>
    <libpart lib="device" part="Q_NPN_BEC">
      <description>Transistor NPN (general)</description>
      <fields>
        <field name="Reference">Q</field>
        <field name="Value">Q_NPN_BEC</field>
      </fields>
      <pins>
        <pin num="1" name="B" type="input"/>
        <pin num="2" name="E" type="passive"/>
        <pin num="3" name="C" type="passive"/>
      </pins>
    </libpart>
    <libpart lib="device" part="Q_PMOS_GDS">
      <description>Transistor P-MOSFET with substrate diode (general)</description>
      <fields>
        <field name="Reference">Q</field>
        <field name="Value">Q_PMOS_GDS</field>
      </fields>
      <pins>
        <pin num="1" name="G" type="input"/>
        <pin num="2" name="D" type="passive"/>
        <pin num="3" name="S" type="passive"/>
      </pins>
    </libpart>
    <libpart lib="device" part="R">
      <description>Resistor</description>
      <footprints>
        <fp>R_*</fp>
        <fp>R_*</fp>
      </footprints>
      <fields>
        <field name="Reference">R</field>
        <field name="Value">R</field>
      </fields>
      <pins>
        <pin num="1" name="~" type="passive"/>
        <pin num="2" name="~" type="passive"/>
      </pins>
    </libpart>
    <libpart lib="switches" part="SW_Push">
      <description>Push button switch, generic, two pins</description>
      <fields>
        <field name="Reference">SW</field>
        <field name="Value">SW_Push</field>
      </fields>
      <pins>
        <pin num="1" name="1" type="passive"/>
        <pin num="2" name="2" type="passive"/>
      </pins>
    </libpart>
    <libpart lib="components" part="TestPoint">
      <description>Test Pont</description>
      <fields>
        <field name="Reference">TP</field>
        <field name="Value">TestPoint</field>
      </fields>
      <pins>
        <pin num="1" name="~" type="passive"/>
      </pins>
    </libpart>
    <libpart lib="Worldsemi" part="WS2812S">
      <aliases>
        <alias>WS2812</alias>
      </aliases>
      <description>RGB LED with integrated controller</description>
      <docs>http://www.world-semi.com/uploads/soft/140305/1-140305113P8.pdf</docs>
      <fields>
        <field name="Reference">LED</field>
        <field name="Value">WS2812S</field>
        <field name="Footprint">LEDs:LED_WS2812-PLCC6</field>
      </fields>
      <pins>
        <pin num="1" name="DOUT" type="output"/>
        <pin num="2" name="DIN" type="input"/>
        <pin num="3" name="VCC" type="power_in"/>
        <pin num="5" name="VDD" type="power_in"/>
        <pin num="6" name="VSS" type="power_in"/>
      </pins>
    </libpart>
  </libparts>
  <libraries>
    <library logical="dc-dc">
      <uri>/usr/share/kicad/library/dc-dc.lib</uri>
    </library>
    <library logical="Worldsemi">
      <uri>/usr/share/kicad/library/Worldsemi.lib</uri>
    </library>
    <library logical="conn">
      <uri>/usr/share/kicad/library/conn.lib</uri>
    </library>
    <library logical="regul">
      <uri>/usr/share/kicad/library/regul.lib</uri>
    </library>
    <library logical="ESP8266">
      <uri>/home/robert/ownCloud/Electronics/Projects/NixieClock_2017/PCB/libraries/kicad-ESP8266/ESP8266.lib</uri>
    </library>
    <library logical="microchip">
      <uri>/usr/share/kicad/library/microchip.lib</uri>
    </library>
    <library logical="components">
      <uri>/home/robert/ownCloud/Electronics/Projects/NixieClock_2017/PCB/libraries/components.lib</uri>
    </library>
    <library logical="opto">
      <uri>/usr/share/kicad/library/opto.lib</uri>
    </library>
    <library logical="switches">
      <uri>/usr/share/kicad/library/switches.lib</uri>
    </library>
    <library logical="device">
      <uri>/usr/share/kicad/library/device.lib</uri>
    </library>
    <library logical="transistors">
      <uri>/usr/share/kicad/library/transistors.lib</uri>
    </library>
    <library logical="mechanical">
      <uri>/usr/share/kicad/library/mechanical.lib</uri>
    </library>
  </libraries>
  <nets>
    <net code="1" name="GND">
      <node ref="C7" pin="2"/>
      <node ref="C8" pin="2"/>
      <node ref="C11" pin="2"/>
      <node ref="R9" pin="2"/>
      <node ref="C9" pin="2"/>
      <node ref="Q4" pin="3"/>
      <node ref="Q5" pin="3"/>
      <node ref="C23" pin="2"/>
      <node ref="RV2" pin="2"/>
      <node ref="J2" pin="1"/>
      <node ref="U4" pin="9"/>
      <node ref="R20" pin="2"/>
      <node ref="U2" pin="4"/>
      <node ref="R6" pin="2"/>
      <node ref="R3" pin="2"/>
      <node ref="C1" pin="2"/>
      <node ref="C4" pin="2"/>
      <node ref="C3" pin="2"/>
      <node ref="C5" pin="2"/>
      <node ref="Q2" pin="3"/>
      <node ref="D1" pin="2"/>
      <node ref="C10" pin="2"/>
      <node ref="C2" pin="2"/>
      <node ref="U1" pin="4"/>
      <node ref="U1" pin="2"/>
      <node ref="Q6" pin="1"/>
      <node ref="U3" pin="4"/>
      <node ref="C25" pin="2"/>
      <node ref="R14" pin="2"/>
      <node ref="C24" pin="2"/>
      <node ref="C18" pin="2"/>
      <node ref="C17" pin="2"/>
      <node ref="Y1" pin="3"/>
      <node ref="C13" pin="2"/>
      <node ref="C15" pin="2"/>
      <node ref="C14" pin="2"/>
      <node ref="BT1" pin="2"/>
      <node ref="C12" pin="2"/>
      <node ref="U5" pin="24"/>
      <node ref="U6" pin="24"/>
      <node ref="Q7" pin="1"/>
      <node ref="C19" pin="2"/>
      <node ref="C20" pin="2"/>
      <node ref="C21" pin="2"/>
      <node ref="J1" pin="2"/>
      <node ref="C22" pin="2"/>
      <node ref="SW1" pin="2"/>
      <node ref="R16" pin="2"/>
      <node ref="SW3" pin="2"/>
      <node ref="SW2" pin="2"/>
      <node ref="SW4" pin="2"/>
      <node ref="R11" pin="2"/>
      <node ref="C16" pin="2"/>
      <node ref="TP5" pin="1"/>
      <node ref="TP6" pin="1"/>
      <node ref="U7" pin="1"/>
      <node ref="LED6" pin="6"/>
      <node ref="LED3" pin="6"/>
      <node ref="LED1" pin="6"/>
      <node ref="LED2" pin="6"/>
      <node ref="C26" pin="2"/>
      <node ref="C6" pin="2"/>
      <node ref="LED4" pin="6"/>
      <node ref="TP2" pin="1"/>
      <node ref="TP3" pin="1"/>
      <node ref="MK2" pin="1"/>
      <node ref="LED5" pin="6"/>
      <node ref="MK1" pin="1"/>
      <node ref="MK3" pin="1"/>
      <node ref="MK4" pin="1"/>
    </net>
    <net code="2" name="/MCU ESP-12/CLK">
      <node ref="Q9" pin="2"/>
      <node ref="TP19" pin="1"/>
      <node ref="U4" pin="13"/>
    </net>
    <net code="3" name="/MCU ESP-12/LED_1">
      <node ref="D4" pin="2"/>
      <node ref="R20" pin="1"/>
      <node ref="U4" pin="10"/>
    </net>
    <net code="4" name="/MCU ESP-12/SDA">
      <node ref="TP13" pin="1"/>
      <node ref="R22" pin="2"/>
      <node ref="U4" pin="11"/>
      <node ref="U3" pin="5"/>
    </net>
    <net code="5" name="/MCU ESP-12/SCL">
      <node ref="R19" pin="2"/>
      <node ref="U3" pin="6"/>
      <node ref="TP12" pin="1"/>
      <node ref="U4" pin="5"/>
    </net>
    <net code="6" name="+12V">
      <node ref="U5" pin="22"/>
      <node ref="U2" pin="8"/>
      <node ref="U2" pin="1"/>
      <node ref="U2" pin="6"/>
      <node ref="U2" pin="7"/>
      <node ref="L2" pin="1"/>
      <node ref="R24" pin="1"/>
      <node ref="R23" pin="1"/>
      <node ref="TP1" pin="1"/>
      <node ref="R25" pin="1"/>
      <node ref="C24" pin="1"/>
      <node ref="C25" pin="1"/>
      <node ref="R47" pin="1"/>
      <node ref="R49" pin="1"/>
      <node ref="U6" pin="25"/>
      <node ref="U6" pin="22"/>
      <node ref="C21" pin="1"/>
      <node ref="C20" pin="1"/>
      <node ref="C19" pin="1"/>
      <node ref="Q7" pin="3"/>
      <node ref="U5" pin="25"/>
      <node ref="Q3" pin="3"/>
      <node ref="U7" pin="3"/>
      <node ref="Q1" pin="3"/>
      <node ref="C9" pin="1"/>
      <node ref="U1" pin="7"/>
      <node ref="C1" pin="1"/>
      <node ref="R1" pin="1"/>
      <node ref="U1" pin="6"/>
      <node ref="C3" pin="1"/>
      <node ref="C7" pin="1"/>
      <node ref="C6" pin="1"/>
    </net>
    <net code="7" name="VCC">
      <node ref="R27" pin="1"/>
      <node ref="R19" pin="1"/>
      <node ref="U4" pin="8"/>
      <node ref="R26" pin="1"/>
      <node ref="TP4" pin="1"/>
      <node ref="R5" pin="1"/>
      <node ref="R17" pin="1"/>
      <node ref="R12" pin="1"/>
      <node ref="C22" pin="1"/>
      <node ref="R13" pin="1"/>
      <node ref="R22" pin="1"/>
      <node ref="R18" pin="1"/>
      <node ref="R21" pin="1"/>
      <node ref="C23" pin="1"/>
      <node ref="L1" pin="2"/>
      <node ref="RV1" pin="3"/>
      <node ref="R28" pin="1"/>
      <node ref="R2" pin="1"/>
      <node ref="C12" pin="1"/>
      <node ref="RV3" pin="1"/>
      <node ref="C5" pin="1"/>
      <node ref="U3" pin="8"/>
    </net>
    <net code="8" name="+HV">
      <node ref="R41" pin="1"/>
      <node ref="R36" pin="1"/>
      <node ref="NE2" pin="2"/>
      <node ref="NE1" pin="2"/>
      <node ref="R39" pin="1"/>
      <node ref="R31" pin="1"/>
      <node ref="TP7" pin="1"/>
      <node ref="R29" pin="1"/>
      <node ref="R7" pin="1"/>
      <node ref="R34" pin="1"/>
      <node ref="D3" pin="1"/>
      <node ref="C11" pin="1"/>
    </net>
    <net code="9" name="/MCU ESP-12/SW_2">
      <node ref="C17" pin="1"/>
      <node ref="U4" pin="7"/>
      <node ref="SW3" pin="1"/>
      <node ref="R12" pin="2"/>
    </net>
    <net code="10" name="/Programmable LEDs/Data_In">
      <node ref="Q11" pin="2"/>
      <node ref="U4" pin="6"/>
      <node ref="R13" pin="2"/>
      <node ref="C18" pin="1"/>
      <node ref="TP27" pin="1"/>
      <node ref="SW2" pin="1"/>
    </net>
    <net code="11" name="/MCU ESP-12/PHOTO">
      <node ref="U4" pin="2"/>
      <node ref="TP16" pin="1"/>
      <node ref="R16" pin="1"/>
      <node ref="R15" pin="2"/>
    </net>
    <net code="12" name="/MCU ESP-12/SW_3">
      <node ref="SW1" pin="1"/>
      <node ref="R21" pin="2"/>
      <node ref="U4" pin="12"/>
      <node ref="C16" pin="1"/>
    </net>
    <net code="13" name="/Nixie Tube drivers/DATA_IN">
      <node ref="Q8" pin="2"/>
      <node ref="TP18" pin="1"/>
      <node ref="U4" pin="4"/>
    </net>
    <net code="14" name="/MCU ESP-12/~BLANK">
      <node ref="Q10" pin="2"/>
      <node ref="U4" pin="14"/>
      <node ref="TP20" pin="1"/>
    </net>
    <net code="15" name="/Nixie Tube drivers/DECIMAL_1">
      <node ref="R33" pin="2"/>
      <node ref="U5" pin="35"/>
    </net>
    <net code="16" name="/Nixie Tube drivers/DECIMAL_2">
      <node ref="R38" pin="2"/>
      <node ref="U6" pin="1"/>
    </net>
    <net code="17" name="/Nixie Tube drivers/COLON_1">
      <node ref="TP25" pin="1"/>
      <node ref="R44" pin="2"/>
      <node ref="U5" pin="34"/>
    </net>
    <net code="18" name="/Nixie Tube drivers/COLON_2">
      <node ref="TP26" pin="1"/>
      <node ref="R46" pin="2"/>
      <node ref="U6" pin="44"/>
    </net>
    <net code="19" name="Net-(RV1-Pad1)">
      <node ref="RV1" pin="1"/>
    </net>
    <net code="20" name="Net-(D1-Pad1)">
      <node ref="Q3" pin="2"/>
      <node ref="D1" pin="1"/>
      <node ref="L1" pin="1"/>
    </net>
    <net code="21" name="Net-(Q1-Pad2)">
      <node ref="Q2" pin="2"/>
      <node ref="Q1" pin="2"/>
      <node ref="Q3" pin="1"/>
    </net>
    <net code="22" name="Net-(C4-Pad1)">
      <node ref="U1" pin="5"/>
      <node ref="C4" pin="1"/>
      <node ref="RV1" pin="2"/>
      <node ref="TP9" pin="1"/>
      <node ref="R2" pin="2"/>
      <node ref="R3" pin="1"/>
    </net>
    <net code="23" name="Net-(C2-Pad1)">
      <node ref="U1" pin="3"/>
      <node ref="C2" pin="1"/>
    </net>
    <net code="24" name="Net-(Q1-Pad1)">
      <node ref="Q2" pin="1"/>
      <node ref="U1" pin="1"/>
      <node ref="R1" pin="2"/>
      <node ref="U1" pin="8"/>
      <node ref="Q1" pin="1"/>
      <node ref="TP8" pin="1"/>
    </net>
    <net code="25" name="Net-(R10-Pad1)">
      <node ref="RV2" pin="3"/>
      <node ref="R10" pin="1"/>
    </net>
    <net code="26" name="Net-(C10-Pad1)">
      <node ref="R9" pin="1"/>
      <node ref="R10" pin="2"/>
      <node ref="TP11" pin="1"/>
      <node ref="C10" pin="1"/>
      <node ref="R8" pin="2"/>
      <node ref="U2" pin="5"/>
    </net>
    <net code="27" name="Net-(R7-Pad2)">
      <node ref="R8" pin="1"/>
      <node ref="R7" pin="2"/>
    </net>
    <net code="28" name="Net-(RV2-Pad1)">
      <node ref="RV2" pin="1"/>
    </net>
    <net code="29" name="Net-(D2-Pad2)">
      <node ref="U2" pin="2"/>
      <node ref="R6" pin="1"/>
      <node ref="Q4" pin="1"/>
      <node ref="D2" pin="2"/>
      <node ref="TP10" pin="1"/>
    </net>
    <net code="30" name="Net-(C8-Pad1)">
      <node ref="C8" pin="1"/>
      <node ref="U2" pin="3"/>
    </net>
    <net code="31" name="Net-(D3-Pad2)">
      <node ref="D3" pin="2"/>
      <node ref="L2" pin="2"/>
      <node ref="Q5" pin="2"/>
    </net>
    <net code="32" name="Net-(D2-Pad1)">
      <node ref="Q5" pin="1"/>
      <node ref="D2" pin="1"/>
      <node ref="Q4" pin="2"/>
    </net>
    <net code="33" name="Net-(R18-Pad2)">
      <node ref="SW4" pin="1"/>
      <node ref="R18" pin="2"/>
      <node ref="U4" pin="1"/>
    </net>
    <net code="34" name="Net-(R17-Pad2)">
      <node ref="U4" pin="3"/>
      <node ref="R17" pin="2"/>
    </net>
    <net code="35" name="/MCU ESP-12/TXD">
      <node ref="J2" pin="3"/>
      <node ref="U4" pin="16"/>
    </net>
    <net code="36" name="/MCU ESP-12/RXD">
      <node ref="J2" pin="2"/>
      <node ref="U4" pin="15"/>
    </net>
    <net code="37" name="Net-(U6-Pad20)">
      <node ref="U6" pin="20"/>
    </net>
    <net code="38" name="Net-(U6-Pad21)">
      <node ref="U6" pin="21"/>
    </net>
    <net code="39" name="Net-(R47-Pad2)">
      <node ref="R47" pin="2"/>
      <node ref="U5" pin="26"/>
    </net>
    <net code="40" name="Net-(TP24-Pad1)">
      <node ref="TP24" pin="1"/>
      <node ref="U6" pin="27"/>
      <node ref="U5" pin="18"/>
    </net>
    <net code="41" name="Net-(R48-Pad2)">
      <node ref="R48" pin="2"/>
      <node ref="U5" pin="28"/>
    </net>
    <net code="42" name="Net-(U5-Pad19)">
      <node ref="U5" pin="19"/>
    </net>
    <net code="43" name="Net-(U5-Pad29)">
      <node ref="U5" pin="29"/>
    </net>
    <net code="44" name="Net-(R50-Pad2)">
      <node ref="R50" pin="2"/>
      <node ref="U6" pin="28"/>
    </net>
    <net code="45" name="Net-(R49-Pad2)">
      <node ref="R49" pin="2"/>
      <node ref="U6" pin="26"/>
    </net>
    <net code="46" name="Net-(U6-Pad18)">
      <node ref="U6" pin="18"/>
    </net>
    <net code="47" name="Net-(U6-Pad19)">
      <node ref="U6" pin="19"/>
    </net>
    <net code="48" name="Net-(U6-Pad29)">
      <node ref="U6" pin="29"/>
    </net>
    <net code="49" name="Net-(Q8-Pad1)">
      <node ref="Q8" pin="1"/>
      <node ref="R26" pin="2"/>
    </net>
    <net code="50" name="Net-(Q9-Pad1)">
      <node ref="R27" pin="2"/>
      <node ref="Q9" pin="1"/>
    </net>
    <net code="51" name="Net-(Q10-Pad1)">
      <node ref="R28" pin="2"/>
      <node ref="Q10" pin="1"/>
    </net>
    <net code="52" name="Net-(Q10-Pad3)">
      <node ref="R25" pin="2"/>
      <node ref="TP22" pin="1"/>
      <node ref="R50" pin="1"/>
      <node ref="R48" pin="1"/>
      <node ref="Q10" pin="3"/>
    </net>
    <net code="53" name="Net-(Q9-Pad3)">
      <node ref="TP21" pin="1"/>
      <node ref="Q9" pin="3"/>
      <node ref="R24" pin="2"/>
      <node ref="U6" pin="23"/>
      <node ref="U5" pin="23"/>
    </net>
    <net code="54" name="Net-(Q8-Pad3)">
      <node ref="Q8" pin="3"/>
      <node ref="U5" pin="27"/>
      <node ref="TP23" pin="1"/>
      <node ref="R23" pin="2"/>
    </net>
    <net code="55" name="Net-(U5-Pad20)">
      <node ref="U5" pin="20"/>
    </net>
    <net code="56" name="Net-(U5-Pad21)">
      <node ref="U5" pin="21"/>
    </net>
    <net code="57" name="Net-(N2-Pad13)">
      <node ref="R33" pin="1"/>
      <node ref="N2" pin="13"/>
    </net>
    <net code="58" name="Net-(N4-Pad13)">
      <node ref="N4" pin="13"/>
      <node ref="R38" pin="1"/>
    </net>
    <net code="59" name="Net-(N1-Pad1)">
      <node ref="N1" pin="1"/>
      <node ref="R30" pin="2"/>
    </net>
    <net code="60" name="Net-(N1-Pad2)">
      <node ref="N1" pin="2"/>
    </net>
    <net code="61" name="Net-(N2-Pad1)">
      <node ref="N2" pin="1"/>
      <node ref="R32" pin="2"/>
    </net>
    <net code="62" name="Net-(N5-Pad13)">
      <node ref="N5" pin="13"/>
    </net>
    <net code="63" name="Net-(N2-Pad2)">
      <node ref="N2" pin="2"/>
    </net>
    <net code="64" name="Net-(N1-Pad13)">
      <node ref="N1" pin="13"/>
    </net>
    <net code="65" name="Net-(N3-Pad1)">
      <node ref="N3" pin="1"/>
      <node ref="R35" pin="2"/>
    </net>
    <net code="66" name="Net-(N3-Pad2)">
      <node ref="N3" pin="2"/>
    </net>
    <net code="67" name="Net-(N3-Pad13)">
      <node ref="N3" pin="13"/>
    </net>
    <net code="68" name="Net-(N5-Pad2)">
      <node ref="N5" pin="2"/>
    </net>
    <net code="69" name="Net-(R29-Pad2)">
      <node ref="R30" pin="1"/>
      <node ref="R29" pin="2"/>
    </net>
    <net code="70" name="Net-(R34-Pad2)">
      <node ref="R35" pin="1"/>
      <node ref="R34" pin="2"/>
    </net>
    <net code="71" name="Net-(N5-Pad1)">
      <node ref="R40" pin="2"/>
      <node ref="N5" pin="1"/>
    </net>
    <net code="72" name="Net-(R39-Pad2)">
      <node ref="R40" pin="1"/>
      <node ref="R39" pin="2"/>
    </net>
    <net code="73" name="Net-(NE2-Pad1)">
      <node ref="NE2" pin="1"/>
      <node ref="R45" pin="1"/>
    </net>
    <net code="74" name="Net-(R45-Pad2)">
      <node ref="R46" pin="1"/>
      <node ref="R45" pin="2"/>
    </net>
    <net code="75" name="Net-(NE1-Pad1)">
      <node ref="NE1" pin="1"/>
      <node ref="R43" pin="1"/>
    </net>
    <net code="76" name="Net-(R43-Pad2)">
      <node ref="R44" pin="1"/>
      <node ref="R43" pin="2"/>
    </net>
    <net code="77" name="Net-(N6-Pad1)">
      <node ref="N6" pin="1"/>
      <node ref="R42" pin="2"/>
    </net>
    <net code="78" name="Net-(R31-Pad2)">
      <node ref="R31" pin="2"/>
      <node ref="R32" pin="1"/>
    </net>
    <net code="79" name="Net-(N4-Pad1)">
      <node ref="R37" pin="2"/>
      <node ref="N4" pin="1"/>
    </net>
    <net code="80" name="Net-(R36-Pad2)">
      <node ref="R36" pin="2"/>
      <node ref="R37" pin="1"/>
    </net>
    <net code="81" name="Net-(R41-Pad2)">
      <node ref="R42" pin="1"/>
      <node ref="R41" pin="2"/>
    </net>
    <net code="82" name="Net-(N6-Pad13)">
      <node ref="N6" pin="13"/>
    </net>
    <net code="83" name="Net-(N4-Pad2)">
      <node ref="N4" pin="2"/>
    </net>
    <net code="84" name="Net-(N6-Pad2)">
      <node ref="N6" pin="2"/>
    </net>
    <net code="85" name="Net-(C15-Pad1)">
      <node ref="U3" pin="2"/>
      <node ref="C15" pin="1"/>
      <node ref="Y1" pin="2"/>
    </net>
    <net code="86" name="/Real Time Clock/BAT_IN">
      <node ref="Q6" pin="3"/>
      <node ref="BT1" pin="1"/>
    </net>
    <net code="87" name="/Real Time Clock/VBAT">
      <node ref="C13" pin="1"/>
      <node ref="TP14" pin="1"/>
      <node ref="Q6" pin="2"/>
      <node ref="U3" pin="3"/>
    </net>
    <net code="88" name="Net-(C14-Pad1)">
      <node ref="Y1" pin="1"/>
      <node ref="C14" pin="1"/>
      <node ref="U3" pin="1"/>
    </net>
    <net code="89" name="Net-(U3-Pad7)">
      <node ref="U3" pin="7"/>
    </net>
    <net code="90" name="Net-(RV3-Pad3)">
      <node ref="RV3" pin="3"/>
    </net>
    <net code="91" name="Net-(R14-Pad1)">
      <node ref="R15" pin="1"/>
      <node ref="TP15" pin="1"/>
      <node ref="RV3" pin="2"/>
      <node ref="R14" pin="1"/>
    </net>
    <net code="92" name="Net-(D4-Pad1)">
      <node ref="D4" pin="1"/>
      <node ref="R11" pin="1"/>
    </net>
    <net code="93" name="Net-(J1-Pad3)">
      <node ref="J1" pin="3"/>
    </net>
    <net code="94" name="/Input power/VIN">
      <node ref="Q7" pin="2"/>
      <node ref="TP17" pin="1"/>
      <node ref="J1" pin="1"/>
    </net>
    <net code="95" name="Net-(LED5-Pad1)">
      <node ref="LED6" pin="2"/>
      <node ref="LED5" pin="1"/>
    </net>
    <net code="96" name="+5V">
      <node ref="TP29" pin="1"/>
      <node ref="U7" pin="2"/>
      <node ref="LED2" pin="5"/>
      <node ref="LED1" pin="3"/>
      <node ref="LED1" pin="5"/>
      <node ref="LED2" pin="3"/>
      <node ref="LED4" pin="5"/>
      <node ref="LED6" pin="3"/>
      <node ref="LED5" pin="5"/>
      <node ref="LED5" pin="3"/>
      <node ref="LED4" pin="3"/>
      <node ref="R4" pin="1"/>
      <node ref="LED3" pin="5"/>
      <node ref="LED3" pin="3"/>
      <node ref="C26" pin="1"/>
      <node ref="LED6" pin="5"/>
    </net>
    <net code="97" name="Net-(LED6-Pad1)">
      <node ref="LED6" pin="1"/>
    </net>
    <net code="98" name="Net-(LED4-Pad1)">
      <node ref="LED5" pin="2"/>
      <node ref="LED4" pin="1"/>
    </net>
    <net code="99" name="Net-(LED1-Pad2)">
      <node ref="LED1" pin="2"/>
      <node ref="Q11" pin="3"/>
      <node ref="R4" pin="2"/>
      <node ref="TP28" pin="1"/>
    </net>
    <net code="100" name="Net-(Q11-Pad1)">
      <node ref="R5" pin="2"/>
      <node ref="Q11" pin="1"/>
    </net>
    <net code="101" name="Net-(LED1-Pad1)">
      <node ref="LED2" pin="2"/>
      <node ref="LED1" pin="1"/>
    </net>
    <net code="102" name="Net-(LED2-Pad1)">
      <node ref="LED2" pin="1"/>
      <node ref="LED3" pin="2"/>
    </net>
    <net code="103" name="Net-(LED3-Pad1)">
      <node ref="LED4" pin="2"/>
      <node ref="LED3" pin="1"/>
    </net>
    <net code="104" name="/Nixie Tube drivers/N6_9">
      <node ref="N6" pin="11"/>
      <node ref="U6" pin="13"/>
    </net>
    <net code="105" name="/Nixie Tube drivers/N6_8">
      <node ref="U6" pin="14"/>
      <node ref="N6" pin="10"/>
    </net>
    <net code="106" name="/Nixie Tube drivers/N6_7">
      <node ref="U6" pin="15"/>
      <node ref="N6" pin="9"/>
    </net>
    <net code="107" name="/Nixie Tube drivers/N4_2">
      <node ref="N4" pin="4"/>
      <node ref="U6" pin="10"/>
    </net>
    <net code="108" name="/Nixie Tube drivers/N5_0">
      <node ref="U6" pin="34"/>
      <node ref="N5" pin="12"/>
    </net>
    <net code="109" name="/Nixie Tube drivers/N4_9">
      <node ref="N4" pin="11"/>
      <node ref="U6" pin="3"/>
    </net>
    <net code="110" name="/Nixie Tube drivers/N4_8">
      <node ref="N4" pin="10"/>
      <node ref="U6" pin="4"/>
    </net>
    <net code="111" name="/Nixie Tube drivers/N4_7">
      <node ref="N4" pin="9"/>
      <node ref="U6" pin="5"/>
    </net>
    <net code="112" name="/Nixie Tube drivers/N4_6">
      <node ref="N4" pin="8"/>
      <node ref="U6" pin="6"/>
    </net>
    <net code="113" name="/Nixie Tube drivers/N4_5">
      <node ref="U6" pin="7"/>
      <node ref="N4" pin="7"/>
    </net>
    <net code="114" name="/Nixie Tube drivers/N4_4">
      <node ref="N4" pin="6"/>
      <node ref="U6" pin="8"/>
    </net>
    <net code="115" name="/Nixie Tube drivers/N4_3">
      <node ref="N4" pin="5"/>
      <node ref="U6" pin="9"/>
    </net>
    <net code="116" name="/Nixie Tube drivers/N5_1">
      <node ref="U6" pin="43"/>
      <node ref="N5" pin="3"/>
    </net>
    <net code="117" name="/Nixie Tube drivers/N4_1">
      <node ref="N4" pin="3"/>
      <node ref="U6" pin="11"/>
    </net>
    <net code="118" name="/Nixie Tube drivers/N4_0">
      <node ref="N4" pin="12"/>
      <node ref="U6" pin="2"/>
    </net>
    <net code="119" name="/Nixie Tube drivers/N3_9">
      <node ref="N3" pin="11"/>
      <node ref="U5" pin="13"/>
    </net>
    <net code="120" name="/Nixie Tube drivers/N3_8">
      <node ref="U5" pin="14"/>
      <node ref="N3" pin="10"/>
    </net>
    <net code="121" name="/Nixie Tube drivers/N3_7">
      <node ref="N3" pin="9"/>
      <node ref="U5" pin="15"/>
    </net>
    <net code="122" name="/Nixie Tube drivers/N3_6">
      <node ref="N3" pin="8"/>
      <node ref="U5" pin="16"/>
    </net>
    <net code="123" name="/Nixie Tube drivers/N3_5">
      <node ref="N3" pin="7"/>
      <node ref="U5" pin="17"/>
    </net>
    <net code="124" name="/Nixie Tube drivers/N5_2">
      <node ref="U6" pin="42"/>
      <node ref="N5" pin="4"/>
    </net>
    <net code="125" name="/Nixie Tube drivers/N5_3">
      <node ref="U6" pin="41"/>
      <node ref="N5" pin="5"/>
    </net>
    <net code="126" name="/Nixie Tube drivers/N5_4">
      <node ref="N5" pin="6"/>
      <node ref="U6" pin="40"/>
    </net>
    <net code="127" name="/Nixie Tube drivers/N5_5">
      <node ref="N5" pin="7"/>
      <node ref="U6" pin="39"/>
    </net>
    <net code="128" name="/Nixie Tube drivers/N5_6">
      <node ref="N5" pin="8"/>
      <node ref="U6" pin="38"/>
    </net>
    <net code="129" name="/Nixie Tube drivers/N5_7">
      <node ref="N5" pin="9"/>
      <node ref="U6" pin="37"/>
    </net>
    <net code="130" name="/Nixie Tube drivers/N5_8">
      <node ref="N5" pin="10"/>
      <node ref="U6" pin="36"/>
    </net>
    <net code="131" name="/Nixie Tube drivers/N5_9">
      <node ref="N5" pin="11"/>
      <node ref="U6" pin="35"/>
    </net>
    <net code="132" name="/Nixie Tube drivers/N6_0">
      <node ref="N6" pin="12"/>
      <node ref="U6" pin="12"/>
    </net>
    <net code="133" name="/Nixie Tube drivers/N6_1">
      <node ref="N6" pin="3"/>
      <node ref="U6" pin="33"/>
    </net>
    <net code="134" name="/Nixie Tube drivers/N6_2">
      <node ref="U6" pin="32"/>
      <node ref="N6" pin="4"/>
    </net>
    <net code="135" name="/Nixie Tube drivers/N6_3">
      <node ref="N6" pin="5"/>
      <node ref="U6" pin="31"/>
    </net>
    <net code="136" name="/Nixie Tube drivers/N6_4">
      <node ref="N6" pin="6"/>
      <node ref="U6" pin="30"/>
    </net>
    <net code="137" name="/Nixie Tube drivers/N6_5">
      <node ref="U6" pin="17"/>
      <node ref="N6" pin="7"/>
    </net>
    <net code="138" name="/Nixie Tube drivers/N6_6">
      <node ref="N6" pin="8"/>
      <node ref="U6" pin="16"/>
    </net>
    <net code="139" name="/Nixie Tube drivers/N1_4">
      <node ref="N1" pin="6"/>
      <node ref="U5" pin="8"/>
    </net>
    <net code="140" name="/Nixie Tube drivers/N1_3">
      <node ref="N1" pin="5"/>
      <node ref="U5" pin="9"/>
    </net>
    <net code="141" name="/Nixie Tube drivers/N1_2">
      <node ref="N1" pin="4"/>
      <node ref="U5" pin="10"/>
    </net>
    <net code="142" name="/Nixie Tube drivers/N1_1">
      <node ref="N1" pin="3"/>
      <node ref="U5" pin="11"/>
    </net>
    <net code="143" name="/Nixie Tube drivers/N1_0">
      <node ref="N1" pin="12"/>
      <node ref="U5" pin="2"/>
    </net>
    <net code="144" name="/Nixie Tube drivers/N1_5">
      <node ref="U5" pin="7"/>
      <node ref="N1" pin="7"/>
    </net>
    <net code="145" name="/Nixie Tube drivers/N2_3">
      <node ref="N2" pin="5"/>
      <node ref="U5" pin="43"/>
    </net>
    <net code="146" name="/Nixie Tube drivers/N3_1">
      <node ref="N3" pin="3"/>
      <node ref="U5" pin="33"/>
    </net>
    <net code="147" name="/Nixie Tube drivers/N3_0">
      <node ref="N3" pin="12"/>
      <node ref="U5" pin="12"/>
    </net>
    <net code="148" name="/Nixie Tube drivers/N2_9">
      <node ref="N2" pin="11"/>
      <node ref="U5" pin="37"/>
    </net>
    <net code="149" name="/Nixie Tube drivers/N2_8">
      <node ref="U5" pin="38"/>
      <node ref="N2" pin="10"/>
    </net>
    <net code="150" name="/Nixie Tube drivers/N2_7">
      <node ref="N2" pin="9"/>
      <node ref="U5" pin="39"/>
    </net>
    <net code="151" name="/Nixie Tube drivers/N2_6">
      <node ref="N2" pin="8"/>
      <node ref="U5" pin="40"/>
    </net>
    <net code="152" name="/Nixie Tube drivers/N2_5">
      <node ref="U5" pin="41"/>
      <node ref="N2" pin="7"/>
    </net>
    <net code="153" name="/Nixie Tube drivers/N2_4">
      <node ref="N2" pin="6"/>
      <node ref="U5" pin="42"/>
    </net>
    <net code="154" name="/Nixie Tube drivers/N2_2">
      <node ref="U5" pin="44"/>
      <node ref="N2" pin="4"/>
    </net>
    <net code="155" name="/Nixie Tube drivers/N2_1">
      <node ref="U5" pin="1"/>
      <node ref="N2" pin="3"/>
    </net>
    <net code="156" name="/Nixie Tube drivers/N2_0">
      <node ref="N2" pin="12"/>
      <node ref="U5" pin="36"/>
    </net>
    <net code="157" name="/Nixie Tube drivers/N1_9">
      <node ref="U5" pin="3"/>
      <node ref="N1" pin="11"/>
    </net>
    <net code="158" name="/Nixie Tube drivers/N1_8">
      <node ref="N1" pin="10"/>
      <node ref="U5" pin="4"/>
    </net>
    <net code="159" name="/Nixie Tube drivers/N1_7">
      <node ref="N1" pin="9"/>
      <node ref="U5" pin="5"/>
    </net>
    <net code="160" name="/Nixie Tube drivers/N1_6">
      <node ref="U5" pin="6"/>
      <node ref="N1" pin="8"/>
    </net>
    <net code="161" name="/Nixie Tube drivers/N3_4">
      <node ref="N3" pin="6"/>
      <node ref="U5" pin="30"/>
    </net>
    <net code="162" name="/Nixie Tube drivers/N3_3">
      <node ref="U5" pin="31"/>
      <node ref="N3" pin="5"/>
    </net>
    <net code="163" name="/Nixie Tube drivers/N3_2">
      <node ref="N3" pin="4"/>
      <node ref="U5" pin="32"/>
    </net>
  </nets>
</export>
